[
  {
    "name": "Transfer",
    "inputs": [
      {
        "type": "address",
        "name": "sender",
        "indexed": true
      },
      {
        "type": "address",
        "name": "receiver",
        "indexed": true
      },
      {
        "type": "uint256",
        "name": "value",
        "indexed": false
      }
    ],
    "anonymous": false,
    "type": "event"
  },
  {
    "name": "Approval",
    "inputs": [
      {
        "type": "address",
        "name": "owner",
        "indexed": true
      },
      {
        "type": "address",
        "name": "spender",
        "indexed": true
      },
      {
        "type": "uint256",
        "name": "value",
        "indexed": false
      }
    ],
    "anonymous": false,
    "type": "event"
  },
  {
    "name": "TokenExchange",
    "inputs": [
      {
        "type": "address",
        "name": "buyer",
        "indexed": true
      },
      {
        "type": "int128",
        "name": "sold_id",
        "indexed": false
      },
      {
        "type": "uint256",
        "name": "tokens_sold",
        "indexed": false
      },
      {
        "type": "int128",
        "name": "bought_id",
        "indexed": false
      },
      {
        "type": "uint256",
        "name": "tokens_bought",
        "indexed": false
      }
    ],
    "anonymous": false,
    "type": "event"
  },
  {
    "name": "AddLiquidity",
    "inputs": [
      {
        "type": "address",
        "name": "provider",
        "indexed": true
      },
      {
        "type": "uint256[2]",
        "name": "token_amounts",
        "indexed": false
      },
      {
        "type": "uint256[2]",
        "name": "fees",
        "indexed": false
      },
      {
        "type": "uint256",
        "name": "invariant",
        "indexed": false
      },
      {
        "type": "uint256",
        "name": "token_supply",
        "indexed": false
      }
    ],
    "anonymous": false,
    "type": "event"
  },
  {
    "name": "RemoveLiquidity",
    "inputs": [
      {
        "type": "address",
        "name": "provider",
        "indexed": true
      },
      {
        "type": "uint256[2]",
        "name": "token_amounts",
        "indexed": false
      },
      {
        "type": "uint256[2]",
        "name": "fees",
        "indexed": false
      },
      {
        "type": "uint256",
        "name": "token_supply",
        "indexed": false
      }
    ],
    "anonymous": false,
    "type": "event"
  },
  {
    "name": "RemoveLiquidityOne",
    "inputs": [
      {
        "type": "address",
        "name": "provider",
        "indexed": true
      },
      {
        "type": "uint256",
        "name": "token_amount",
        "indexed": false
      },
      {
        "type": "uint256",
        "name": "coin_amount",
        "indexed": false
      },
      {
        "type": "uint256",
        "name": "token_supply",
        "indexed": false
      }
    ],
    "anonymous": false,
    "type": "event"
  },
  {
    "name": "RemoveLiquidityImbalance",
    "inputs": [
      {
        "type": "address",
        "name": "provider",
        "indexed": true
      },
      {
        "type": "uint256[2]",
        "name": "token_amounts",
        "indexed": false
      },
      {
        "type": "uint256[2]",
        "name": "fees",
        "indexed": false
      },
      {
        "type": "uint256",
        "name": "invariant",
        "indexed": false
      },
      {
        "type": "uint256",
        "name": "token_supply",
        "indexed": false
      }
    ],
    "anonymous": false,
    "type": "event"
  },
  {
    "name": "CommitNewAdmin",
    "inputs": [
      {
        "type": "uint256",
        "name": "deadline",
        "indexed": true
      },
      {
        "type": "address",
        "name": "admin",
        "indexed": true
      }
    ],
    "anonymous": false,
    "type": "event"
  },
  {
    "name": "NewAdmin",
    "inputs": [
      {
        "type": "address",
        "name": "admin",
        "indexed": true
      }
    ],
    "anonymous": false,
    "type": "event"
  },
  {
    "name": "CommitNewFee",
    "inputs": [
      {
        "type": "uint256",
        "name": "deadline",
        "indexed": true
      },
      {
        "type": "uint256",
        "name": "fee",
        "indexed": false
      },
      {
        "type": "uint256",
        "name": "admin_fee",
        "indexed": false
      }
    ],
    "anonymous": false,
    "type": "event"
  },
  {
    "name": "NewFee",
    "inputs": [
      {
        "type": "uint256",
        "name": "fee",
        "indexed": false
      },
      {
        "type": "uint256",
        "name": "admin_fee",
        "indexed": false
      }
    ],
    "anonymous": false,
    "type": "event"
  },
  {
    "name": "RampA",
    "inputs": [
      {
        "type": "uint256",
        "name": "old_A",
        "indexed": false
      },
      {
        "type": "uint256",
        "name": "new_A",
        "indexed": false
      },
      {
        "type": "uint256",
        "name": "initial_time",
        "indexed": false
      },
      {
        "type": "uint256",
        "name": "future_time",
        "indexed": false
      }
    ],
    "anonymous": false,
    "type": "event"
  },
  {
    "name": "StopRampA",
    "inputs": [
      {
        "type": "uint256",
        "name": "A",
        "indexed": false
      },
      {
        "type": "uint256",
        "name": "t",
        "indexed": false
      }
    ],
    "anonymous": false,
    "type": "event"
  },
  {
    "outputs": [],
    "inputs": [
      {
        "type": "string",
        "name": "_name"
      },
      {
        "type": "string",
        "name": "_symbol"
      },
      {
        "type": "address",
        "name": "_owner"
      },
      {
        "type": "address[2]",
        "name": "_coins"
      },
      {
        "type": "uint256",
        "name": "_A"
      },
      {
        "type": "uint256",
        "name": "_fee"
      },
      {
        "type": "uint256",
        "name": "_admin_fee"
      }
    ],
    "stateMutability": "nonpayable",
    "type": "constructor"
  },
  {
    "name": "decimals",
    "outputs": [
      {
        "type": "uint256",
        "name": ""
      }
    ],
    "inputs": [],
    "stateMutability": "view",
    "type": "function",
    "gas": "261"
  },
  {
    "name": "transfer",
    "outputs": [
      {
        "type": "bool",
        "name": ""
      }
    ],
    "inputs": [
      {
        "type": "address",
        "name": "_to"
      },
      {
        "type": "uint256",
        "name": "_value"
      }
    ],
    "stateMutability": "nonpayable",
    "type": "function",
    "gas": "74713"
  },
  {
    "name": "transferFrom",
    "outputs": [
      {
        "type": "bool",
        "name": ""
      }
    ],
    "inputs": [
      {
        "type": "address",
        "name": "_from"
      },
      {
        "type": "address",
        "name": "_to"
      },
      {
        "type": "uint256",
        "name": "_value"
      }
    ],
    "stateMutability": "nonpayable",
    "type": "function",
    "gas": "111355"
  },
  {
    "name": "approve",
    "outputs": [
      {
        "type": "bool",
        "name": ""
      }
    ],
    "inputs": [
      {
        "type": "address",
        "name": "_spender"
      },
      {
        "type": "uint256",
        "name": "_value"
      }
    ],
    "stateMutability": "nonpayable",
    "type": "function",
    "gas": "37794"
  },
  {
    "name": "A",
    "outputs": [
      {
        "type": "uint256",
        "name": ""
      }
    ],
    "inputs": [],
    "stateMutability": "view",
    "type": "function",
    "gas": "5439"
  },
  {
    "name": "A_precise",
    "outputs": [
      {
        "type": "uint256",
        "name": ""
      }
    ],
    "inputs": [],
    "stateMutability": "view",
    "type": "function",
    "gas": "5401"
  },
  {
    "name": "get_virtual_price",
    "outputs": [
      {
        "type": "uint256",
        "name": ""
      }
    ],
    "inputs": [],
    "stateMutability": "view",
    "type": "function",
    "gas": "1009729"
  },
  {
    "name": "calc_token_amount",
    "outputs": [
      {
        "type": "uint256",
        "name": ""
      }
    ],
    "inputs": [
      {
        "type": "uint256[2]",
        "name": "_amounts"
      },
      {
        "type": "bool",
        "name": "_is_deposit"
      }
    ],
    "stateMutability": "view",
    "type": "function",
    "gas": "4016564"
  },
  {
    "name": "add_liquidity",
    "outputs": [
      {
        "type": "uint256",
        "name": ""
      }
    ],
    "inputs": [
      {
        "type": "uint256[2]",
        "name": "_amounts"
      },
      {
        "type": "uint256",
        "name": "_min_mint_amount"
      }
    ],
    "stateMutability": "nonpayable",
    "type": "function",
    "gas": "6262149"
  },
  {
    "name": "get_dy",
    "outputs": [
      {
        "type": "uint256",
        "name": ""
      }
    ],
    "inputs": [
      {
        "type": "int128",
        "name": "i"
      },
      {
        "type": "int128",
        "name": "j"
      },
      {
        "type": "uint256",
        "name": "_dx"
      }
    ],
    "stateMutability": "view",
    "type": "function",
    "gas": "2447901"
  },
  {
    "name": "exchange",
    "outputs": [
      {
        "type": "uint256",
        "name": ""
      }
    ],
    "inputs": [
      {
        "type": "int128",
        "name": "i"
      },
      {
        "type": "int128",
        "name": "j"
      },
      {
        "type": "uint256",
        "name": "_dx"
      },
      {
        "type": "uint256",
        "name": "_min_dy"
      }
    ],
    "stateMutability": "nonpayable",
    "type": "function",
    "gas": "2610850"
  },
  {
    "name": "remove_liquidity",
    "outputs": [
      {
        "type": "uint256[2]",
        "name": ""
      }
    ],
    "inputs": [
      {
        "type": "uint256",
        "name": "_amount"
      },
      {
        "type": "uint256[2]",
        "name": "_min_amounts"
      }
    ],
    "stateMutability": "nonpayable",
    "type": "function",
    "gas": "238744"
  },
  {
    "name": "remove_liquidity_imbalance",
    "outputs": [
      {
        "type": "uint256",
        "name": ""
      }
    ],
    "inputs": [
      {
        "type": "uint256[2]",
        "name": "_amounts"
      },
      {
        "type": "uint256",
        "name": "_max_burn_amount"
      }
    ],
    "stateMutability": "nonpayable",
    "type": "function",
    "gas": "6261825"
  },
  {
    "name": "calc_withdraw_one_coin",
    "outputs": [
      {
        "type": "uint256",
        "name": ""
      }
    ],
    "inputs": [
      {
        "type": "uint256",
        "name": "_token_amount"
      },
      {
        "type": "int128",
        "name": "i"
      }
    ],
    "stateMutability": "view",
    "type": "function",
    "gas": "1609"
  },
  {
    "name": "remove_liquidity_one_coin",
    "outputs": [
      {
        "type": "uint256",
        "name": ""
      }
    ],
    "inputs": [
      {
        "type": "uint256",
        "name": "_token_amount"
      },
      {
        "type": "int128",
        "name": "i"
      },
      {
        "type": "uint256",
        "name": "_min_amount"
      }
    ],
    "stateMutability": "nonpayable",
    "type": "function",
    "gas": "3947982"
  },
  {
    "name": "ramp_A",
    "outputs": [],
    "inputs": [
      {
        "type": "uint256",
        "name": "_future_A"
      },
      {
        "type": "uint256",
        "name": "_future_time"
      }
    ],
    "stateMutability": "nonpayable",
    "type": "function",
    "gas": "152014"
  },
  {
    "name": "stop_ramp_A",
    "outputs": [],
    "inputs": [],
    "stateMutability": "nonpayable",
    "type": "function",
    "gas": "148775"
  },
  {
    "name": "commit_new_fee",
    "outputs": [],
    "inputs": [
      {
        "type": "uint256",
        "name": "_new_fee"
      },
      {
        "type": "uint256",
        "name": "_new_admin_fee"
      }
    ],
    "stateMutability": "nonpayable",
    "type": "function",
    "gas": "110491"
  },
  {
    "name": "apply_new_fee",
    "outputs": [],
    "inputs": [],
    "stateMutability": "nonpayable",
    "type": "function",
    "gas": "97272"
  },
  {
    "name": "revert_new_parameters",
    "outputs": [],
    "inputs": [],
    "stateMutability": "nonpayable",
    "type": "function",
    "gas": "21925"
  },
  {
    "name": "commit_transfer_ownership",
    "outputs": [],
    "inputs": [
      {
        "type": "address",
        "name": "_owner"
      }
    ],
    "stateMutability": "nonpayable",
    "type": "function",
    "gas": "74663"
  },
  {
    "name": "apply_transfer_ownership",
    "outputs": [],
    "inputs": [],
    "stateMutability": "nonpayable",
    "type": "function",
    "gas": "60740"
  },
  {
    "name": "revert_transfer_ownership",
    "outputs": [],
    "inputs": [],
    "stateMutability": "nonpayable",
    "type": "function",
    "gas": "22015"
  },
  {
    "name": "admin_balances",
    "outputs": [
      {
        "type": "uint256",
        "name": ""
      }
    ],
    "inputs": [
      {
        "type": "uint256",
        "name": "i"
      }
    ],
    "stateMutability": "view",
    "type": "function",
    "gas": "3511"
  },
  {
    "name": "withdraw_admin_fees",
    "outputs": [],
    "inputs": [],
    "stateMutability": "nonpayable",
    "type": "function",
    "gas": "15067"
  },
  {
    "name": "donate_admin_fees",
    "outputs": [],
    "inputs": [],
    "stateMutability": "nonpayable",
    "type": "function",
    "gas": "74995"
  },
  {
    "name": "kill_me",
    "outputs": [],
    "inputs": [],
    "stateMutability": "nonpayable",
    "type": "function",
    "gas": "38028"
  },
  {
    "name": "unkill_me",
    "outputs": [],
    "inputs": [],
    "stateMutability": "nonpayable",
    "type": "function",
    "gas": "22165"
  },
  {
    "name": "coins",
    "outputs": [
      {
        "type": "address",
        "name": ""
      }
    ],
    "inputs": [
      {
        "type": "uint256",
        "name": "arg0"
      }
    ],
    "stateMutability": "view",
    "type": "function",
    "gas": "2250"
  },
  {
    "name": "balances",
    "outputs": [
      {
        "type": "uint256",
        "name": ""
      }
    ],
    "inputs": [
      {
        "type": "uint256",
        "name": "arg0"
      }
    ],
    "stateMutability": "view",
    "type": "function",
    "gas": "2280"
  },
  {
    "name": "fee",
    "outputs": [
      {
        "type": "uint256",
        "name": ""
      }
    ],
    "inputs": [],
    "stateMutability": "view",
    "type": "function",
    "gas": "2201"
  },
  {
    "name": "admin_fee",
    "outputs": [
      {
        "type": "uint256",
        "name": ""
      }
    ],
    "inputs": [],
    "stateMutability": "view",
    "type": "function",
    "gas": "2231"
  },
  {
    "name": "owner",
    "outputs": [
      {
        "type": "address",
        "name": ""
      }
    ],
    "inputs": [],
    "stateMutability": "view",
    "type": "function",
    "gas": "2261"
  },
  {
    "name": "initial_A",
    "outputs": [
      {
        "type": "uint256",
        "name": ""
      }
    ],
    "inputs": [],
    "stateMutability": "view",
    "type": "function",
    "gas": "2291"
  },
  {
    "name": "future_A",
    "outputs": [
      {
        "type": "uint256",
        "name": ""
      }
    ],
    "inputs": [],
    "stateMutability": "view",
    "type": "function",
    "gas": "2321"
  },
  {
    "name": "initial_A_time",
    "outputs": [
      {
        "type": "uint256",
        "name": ""
      }
    ],
    "inputs": [],
    "stateMutability": "view",
    "type": "function",
    "gas": "2351"
  },
  {
    "name": "future_A_time",
    "outputs": [
      {
        "type": "uint256",
        "name": ""
      }
    ],
    "inputs": [],
    "stateMutability": "view",
    "type": "function",
    "gas": "2381"
  },
  {
    "name": "admin_actions_deadline",
    "outputs": [
      {
        "type": "uint256",
        "name": ""
      }
    ],
    "inputs": [],
    "stateMutability": "view",
    "type": "function",
    "gas": "2411"
  },
  {
    "name": "transfer_ownership_deadline",
    "outputs": [
      {
        "type": "uint256",
        "name": ""
      }
    ],
    "inputs": [],
    "stateMutability": "view",
    "type": "function",
    "gas": "2441"
  },
  {
    "name": "future_fee",
    "outputs": [
      {
        "type": "uint256",
        "name": ""
      }
    ],
    "inputs": [],
    "stateMutability": "view",
    "type": "function",
    "gas": "2471"
  },
  {
    "name": "future_admin_fee",
    "outputs": [
      {
        "type": "uint256",
        "name": ""
      }
    ],
    "inputs": [],
    "stateMutability": "view",
    "type": "function",
    "gas": "2501"
  },
  {
    "name": "future_owner",
    "outputs": [
      {
        "type": "address",
        "name": ""
      }
    ],
    "inputs": [],
    "stateMutability": "view",
    "type": "function",
    "gas": "2531"
  },
  {
    "name": "name",
    "outputs": [
      {
        "type": "string",
        "name": ""
      }
    ],
    "inputs": [],
    "stateMutability": "view",
    "type": "function",
    "gas": "8963"
  },
  {
    "name": "symbol",
    "outputs": [
      {
        "type": "string",
        "name": ""
      }
    ],
    "inputs": [],
    "stateMutability": "view",
    "type": "function",
    "gas": "8016"
  },
  {
    "name": "balanceOf",
    "outputs": [
      {
        "type": "uint256",
        "name": ""
      }
    ],
    "inputs": [
      {
        "type": "address",
        "name": "arg0"
      }
    ],
    "stateMutability": "view",
    "type": "function",
    "gas": "2836"
  },
  {
    "name": "allowance",
    "outputs": [
      {
        "type": "uint256",
        "name": ""
      }
    ],
    "inputs": [
      {
        "type": "address",
        "name": "arg0"
      },
      {
        "type": "address",
        "name": "arg1"
      }
    ],
    "stateMutability": "view",
    "type": "function",
    "gas": "3081"
  },
  {
    "name": "totalSupply",
    "outputs": [
      {
        "type": "uint256",
        "name": ""
      }
    ],
    "inputs": [],
    "stateMutability": "view",
    "type": "function",
    "gas": "2681"
  }
]