{"expireTime":9007200881073042000,"key":"remark-check-links-f81bad31-ad37-58c3-a680-e3377323db03-6f017827335a719c4ae9bc04552114a9","val":{"path":"/resources/installation/overview/","links":[{"type":"link","title":null,"url":"/strategies/celo-arb/","children":[{"type":"text","value":"Celo Arbitrage","position":{"start":{"line":36,"column":58,"offset":3794},"end":{"line":36,"column":72,"offset":3808},"indent":[]}}],"position":{"start":{"line":36,"column":57,"offset":3793},"end":{"line":36,"column":96,"offset":3832},"indent":[]},"frontmatter":{"title":"Overview","description":null}},{"type":"link","title":null,"url":"/resources/installation/updating/","children":[{"type":"text","value":"Update/Revert Hummingbot","position":{"start":{"line":44,"column":67,"offset":4216},"end":{"line":44,"column":91,"offset":4240},"indent":[]}}],"position":{"start":{"line":44,"column":66,"offset":4215},"end":{"line":44,"column":102,"offset":4251},"indent":[]},"frontmatter":{"title":"Overview","description":null}}],"headings":["supported-installation-environments","for-cloud","update-hummingbot"],"setAt":1626332051400}}