{"expireTime":9007200881073039000,"key":"remark-check-links-5deb2544-fdad-5fef-a1cb-f11ed259da20-3e1ea04464400ba56a1abc19803e803c","val":{"path":"/scripts/overview/","links":[{"type":"link","title":null,"url":"/release-notes/0.29.0","children":[{"type":"text","value":"Scripts","position":{"start":{"line":68,"column":96,"offset":2109},"end":{"line":68,"column":103,"offset":2116},"indent":[]}}],"position":{"start":{"line":68,"column":95,"offset":2108},"end":{"line":68,"column":127,"offset":2140},"indent":[]},"frontmatter":{"title":"Overview","description":"Learn how to use scripts"}}],"headings":["language","how-it-works","create-your-own-script","updating-your-scripts","linux","macos"],"setAt":1626332048616}}