{"expireTime":9007200881073046000,"key":"gatsby-plugin-mdx-entire-payload-bf98becc6802a45059b3f4f62afcc41d-","val":{"mdast":{"type":"root","children":[{"type":"paragraph","children":[{"type":"text","value":"🚀 Welcome to ","position":{"start":{"line":2,"column":1,"offset":1},"end":{"line":2,"column":15,"offset":15},"indent":[]}},{"type":"inlineCode","value":"hummingbot","position":{"start":{"line":2,"column":15,"offset":15},"end":{"line":2,"column":27,"offset":27},"indent":[]}},{"type":"text","value":" version 0.23.0! In this release, we are excited to announce the open beta of Liquidity Mining, a new connector, easier to use pure market-making strategy, and addressed a number of bugs.","position":{"start":{"line":2,"column":27,"offset":27},"end":{"line":2,"column":214,"offset":214},"indent":[]}}],"position":{"start":{"line":2,"column":1,"offset":1},"end":{"line":2,"column":214,"offset":214},"indent":[]}},{"type":"heading","depth":2,"children":[{"type":"text","value":"🌊⛏ Liquidity mining open beta","position":{"start":{"line":4,"column":4,"offset":219},"end":{"line":4,"column":34,"offset":249},"indent":[]}}],"position":{"start":{"line":4,"column":1,"offset":216},"end":{"line":4,"column":34,"offset":249},"indent":[]}},{"type":"paragraph","children":[{"type":"text","value":"We are excited to launch the Liquidity Mining Open Beta today! We welcome anyone interested in joining us during the 4-week testing period and try the ","position":{"start":{"line":6,"column":1,"offset":251},"end":{"line":6,"column":152,"offset":402},"indent":[]}},{"type":"link","title":null,"url":"https://miners.hummingbot.io","children":[{"type":"text","value":"Hummingbot Miners App","position":{"start":{"line":6,"column":153,"offset":403},"end":{"line":6,"column":174,"offset":424},"indent":[]}}],"position":{"start":{"line":6,"column":152,"offset":402},"end":{"line":6,"column":205,"offset":455},"indent":[]}},{"type":"text","value":". We will work hard to collect user feedback and fix bugs to provide a great user experience when we go live on March 2, 2020.","position":{"start":{"line":6,"column":205,"offset":455},"end":{"line":6,"column":331,"offset":581},"indent":[]}}],"position":{"start":{"line":6,"column":1,"offset":251},"end":{"line":6,"column":331,"offset":581},"indent":[]}},{"type":"list","ordered":false,"start":null,"spread":false,"children":[{"type":"listItem","spread":false,"checked":null,"children":[{"type":"paragraph","children":[{"type":"link","title":null,"url":"https://hummingbot.io/liquidity-mining/","children":[{"type":"text","value":"Learn more","position":{"start":{"line":8,"column":4,"offset":586},"end":{"line":8,"column":14,"offset":596},"indent":[]}}],"position":{"start":{"line":8,"column":3,"offset":585},"end":{"line":8,"column":56,"offset":638},"indent":[]}}],"position":{"start":{"line":8,"column":3,"offset":585},"end":{"line":8,"column":56,"offset":638},"indent":[]}}],"position":{"start":{"line":8,"column":1,"offset":583},"end":{"line":8,"column":56,"offset":638},"indent":[]}}],"position":{"start":{"line":8,"column":1,"offset":583},"end":{"line":8,"column":56,"offset":638},"indent":[]}},{"type":"heading","depth":3,"children":[{"type":"text","value":"🧪 User testing during open beta","position":{"start":{"line":10,"column":5,"offset":644},"end":{"line":10,"column":37,"offset":676},"indent":[]}}],"position":{"start":{"line":10,"column":1,"offset":640},"end":{"line":10,"column":37,"offset":676},"indent":[]}},{"type":"paragraph","children":[{"type":"text","value":"We are inviting interested users to join our dedicated user testing program during the Open Beta period. Testers will receive ","position":{"start":{"line":12,"column":1,"offset":678},"end":{"line":12,"column":127,"offset":804},"indent":[]}},{"type":"strong","children":[{"type":"text","value":"0.1 ETH","position":{"start":{"line":12,"column":129,"offset":806},"end":{"line":12,"column":136,"offset":813},"indent":[]}}],"position":{"start":{"line":12,"column":127,"offset":804},"end":{"line":12,"column":138,"offset":815},"indent":[]}},{"type":"text","value":" for their time.","position":{"start":{"line":12,"column":138,"offset":815},"end":{"line":12,"column":154,"offset":831},"indent":[]}}],"position":{"start":{"line":12,"column":1,"offset":678},"end":{"line":12,"column":154,"offset":831},"indent":[]}},{"type":"paragraph","children":[{"type":"text","value":"For users who want to participate, please fill out this form. We’ll reach out to you soon!","position":{"start":{"line":14,"column":1,"offset":833},"end":{"line":14,"column":91,"offset":923},"indent":[]}}],"position":{"start":{"line":14,"column":1,"offset":833},"end":{"line":14,"column":91,"offset":923},"indent":[]}},{"type":"paragraph","children":[{"type":"text","value":"Please refer to the following links and resources for more information:","position":{"start":{"line":16,"column":1,"offset":925},"end":{"line":16,"column":72,"offset":996},"indent":[]}}],"position":{"start":{"line":16,"column":1,"offset":925},"end":{"line":16,"column":72,"offset":996},"indent":[]}},{"type":"list","ordered":false,"start":null,"spread":false,"children":[{"type":"listItem","spread":false,"checked":null,"children":[{"type":"paragraph","children":[{"type":"link","title":null,"url":"https://miners.hummingbot.io","children":[{"type":"text","value":"Hummingbot Miners","position":{"start":{"line":18,"column":4,"offset":1001},"end":{"line":18,"column":21,"offset":1018},"indent":[]}}],"position":{"start":{"line":18,"column":3,"offset":1000},"end":{"line":18,"column":52,"offset":1049},"indent":[]}}],"position":{"start":{"line":18,"column":3,"offset":1000},"end":{"line":18,"column":52,"offset":1049},"indent":[]}}],"position":{"start":{"line":18,"column":1,"offset":998},"end":{"line":18,"column":52,"offset":1049},"indent":[]}},{"type":"listItem","spread":false,"checked":null,"children":[{"type":"paragraph","children":[{"type":"link","title":null,"url":"https://docs.hummingbot.io/miner/liquidity-mining/overview/","children":[{"type":"text","value":"Participation Guide","position":{"start":{"line":19,"column":4,"offset":1053},"end":{"line":19,"column":23,"offset":1072},"indent":[]}}],"position":{"start":{"line":19,"column":3,"offset":1052},"end":{"line":19,"column":85,"offset":1134},"indent":[]}}],"position":{"start":{"line":19,"column":3,"offset":1052},"end":{"line":19,"column":85,"offset":1134},"indent":[]}}],"position":{"start":{"line":19,"column":1,"offset":1050},"end":{"line":19,"column":85,"offset":1134},"indent":[]}},{"type":"listItem","spread":false,"checked":null,"children":[{"type":"paragraph","children":[{"type":"link","title":null,"url":"https://support.hummingbot.io/hc/en-us","children":[{"type":"text","value":"Hummingbot Help Center","position":{"start":{"line":20,"column":4,"offset":1138},"end":{"line":20,"column":26,"offset":1160},"indent":[]}}],"position":{"start":{"line":20,"column":3,"offset":1137},"end":{"line":20,"column":67,"offset":1201},"indent":[]}}],"position":{"start":{"line":20,"column":3,"offset":1137},"end":{"line":20,"column":67,"offset":1201},"indent":[]}}],"position":{"start":{"line":20,"column":1,"offset":1135},"end":{"line":20,"column":67,"offset":1201},"indent":[]}},{"type":"listItem","spread":false,"checked":null,"children":[{"type":"paragraph","children":[{"type":"link","title":null,"url":"https://hummingbot.io/liquidity-mining-policy/","children":[{"type":"text","value":"Liquidity Mining Policy","position":{"start":{"line":21,"column":4,"offset":1205},"end":{"line":21,"column":27,"offset":1228},"indent":[]}}],"position":{"start":{"line":21,"column":3,"offset":1204},"end":{"line":21,"column":76,"offset":1277},"indent":[]}}],"position":{"start":{"line":21,"column":3,"offset":1204},"end":{"line":21,"column":76,"offset":1277},"indent":[]}}],"position":{"start":{"line":21,"column":1,"offset":1202},"end":{"line":21,"column":76,"offset":1277},"indent":[]}}],"position":{"start":{"line":18,"column":1,"offset":998},"end":{"line":21,"column":76,"offset":1277},"indent":[1,1,1]}},{"type":"heading","depth":2,"children":[{"type":"text","value":"📊 Pure market-making configuration simplified","position":{"start":{"line":23,"column":4,"offset":1282},"end":{"line":23,"column":50,"offset":1328},"indent":[]}}],"position":{"start":{"line":23,"column":1,"offset":1279},"end":{"line":23,"column":50,"offset":1328},"indent":[]}},{"type":"paragraph","children":[{"type":"text","value":"Pure market-making now has a basic/advanced split that will only prompt during the configuration of the basic parameters such as the exchange name, trading pair, bid/ask spreads, cancel order wait time, and order amount.","position":{"start":{"line":25,"column":1,"offset":1330},"end":{"line":25,"column":221,"offset":1550},"indent":[]}}],"position":{"start":{"line":25,"column":1,"offset":1330},"end":{"line":25,"column":221,"offset":1550},"indent":[]}},{"type":"paragraph","children":[{"type":"text","value":"Users can configure the advanced features of this strategy by entering ","position":{"start":{"line":27,"column":1,"offset":1552},"end":{"line":27,"column":72,"offset":1623},"indent":[]}},{"type":"inlineCode","value":"Yes","position":{"start":{"line":27,"column":72,"offset":1623},"end":{"line":27,"column":77,"offset":1628},"indent":[]}},{"type":"text","value":" when prompted via ","position":{"start":{"line":27,"column":77,"offset":1628},"end":{"line":27,"column":96,"offset":1647},"indent":[]}},{"type":"inlineCode","value":"config <parameter>","position":{"start":{"line":27,"column":96,"offset":1647},"end":{"line":27,"column":116,"offset":1667},"indent":[]}},{"type":"text","value":" command in Hummingbot, or by editing the strategy config file.","position":{"start":{"line":27,"column":116,"offset":1667},"end":{"line":27,"column":179,"offset":1730},"indent":[]}}],"position":{"start":{"line":27,"column":1,"offset":1552},"end":{"line":27,"column":179,"offset":1730},"indent":[]}},{"type":"paragraph","children":[{"type":"text","value":"More information about ","position":{"start":{"line":29,"column":1,"offset":1732},"end":{"line":29,"column":24,"offset":1755},"indent":[]}},{"type":"link","title":null,"url":"https://docs.hummingbot.io/strategies/pure-market-making/#basic-mode","children":[{"type":"text","value":"Basic Mode","position":{"start":{"line":29,"column":25,"offset":1756},"end":{"line":29,"column":35,"offset":1766},"indent":[]}}],"position":{"start":{"line":29,"column":24,"offset":1755},"end":{"line":29,"column":106,"offset":1837},"indent":[]}},{"type":"text","value":" and ","position":{"start":{"line":29,"column":106,"offset":1837},"end":{"line":29,"column":111,"offset":1842},"indent":[]}},{"type":"link","title":null,"url":"https://docs.hummingbot.io/strategies/pure-market-making/#advanced-mode","children":[{"type":"text","value":"Advanced Mode","position":{"start":{"line":29,"column":112,"offset":1843},"end":{"line":29,"column":125,"offset":1856},"indent":[]}}],"position":{"start":{"line":29,"column":111,"offset":1842},"end":{"line":29,"column":199,"offset":1930},"indent":[]}},{"type":"text","value":" of Pure Market Making in our User Manual.","position":{"start":{"line":29,"column":199,"offset":1930},"end":{"line":29,"column":241,"offset":1972},"indent":[]}}],"position":{"start":{"line":29,"column":1,"offset":1732},"end":{"line":29,"column":241,"offset":1972},"indent":[]}},{"type":"heading","depth":2,"children":[{"type":"text","value":"🔗 New KuCoin connector","position":{"start":{"line":31,"column":4,"offset":1977},"end":{"line":31,"column":27,"offset":2000},"indent":[]}}],"position":{"start":{"line":31,"column":1,"offset":1974},"end":{"line":31,"column":27,"offset":2000},"indent":[]}},{"type":"paragraph","children":[{"type":"text","value":"Hummingbot now supports ","position":{"start":{"line":33,"column":1,"offset":2002},"end":{"line":33,"column":25,"offset":2026},"indent":[]}},{"type":"link","title":null,"url":"https://www.kucoin.com/","children":[{"type":"text","value":"KuCoin","position":{"start":{"line":33,"column":26,"offset":2027},"end":{"line":33,"column":32,"offset":2033},"indent":[]}}],"position":{"start":{"line":33,"column":25,"offset":2026},"end":{"line":33,"column":58,"offset":2059},"indent":[]}},{"type":"text","value":" exchange! Nicknamed the \"People's Exchange\"​, Kucoin is easy to use for novice investors and in-depth enough for crypto enthusiasts. It has one of the world’s most impressive trading pair selections, a wide range of alt coins with more than 300 trading pairs and are adding new ones regularly.","position":{"start":{"line":33,"column":58,"offset":2059},"end":{"line":33,"column":352,"offset":2353},"indent":[]}}],"position":{"start":{"line":33,"column":1,"offset":2002},"end":{"line":33,"column":352,"offset":2353},"indent":[]}},{"type":"paragraph","children":[{"type":"text","value":"Read more about using KuCoin connector in the ","position":{"start":{"line":35,"column":1,"offset":2355},"end":{"line":35,"column":47,"offset":2401},"indent":[]}},{"type":"link","title":null,"url":"/spot-connectors/kucoin/","children":[{"type":"text","value":"User Manual","position":{"start":{"line":35,"column":48,"offset":2402},"end":{"line":35,"column":59,"offset":2413},"indent":[]}}],"position":{"start":{"line":35,"column":47,"offset":2401},"end":{"line":35,"column":86,"offset":2440},"indent":[]}},{"type":"text","value":".","position":{"start":{"line":35,"column":86,"offset":2440},"end":{"line":35,"column":87,"offset":2441},"indent":[]}}],"position":{"start":{"line":35,"column":1,"offset":2355},"end":{"line":35,"column":87,"offset":2441},"indent":[]}},{"type":"heading","depth":2,"children":[{"type":"text","value":"📜 Error log collection","position":{"start":{"line":37,"column":4,"offset":2446},"end":{"line":37,"column":27,"offset":2469},"indent":[]}}],"position":{"start":{"line":37,"column":1,"offset":2443},"end":{"line":37,"column":27,"offset":2469},"indent":[]}},{"type":"paragraph","children":[{"type":"text","value":"Instead of using the old ","position":{"start":{"line":39,"column":1,"offset":2471},"end":{"line":39,"column":26,"offset":2496},"indent":[]}},{"type":"inlineCode","value":"hummingbot_logs.yml","position":{"start":{"line":39,"column":26,"offset":2496},"end":{"line":39,"column":47,"offset":2517},"indent":[]}},{"type":"text","value":" templates for sending logs, we now added a prompt in Hummingbot that allows users to enable or disabled sending errors logs.","position":{"start":{"line":39,"column":47,"offset":2517},"end":{"line":39,"column":172,"offset":2642},"indent":[]}}],"position":{"start":{"line":39,"column":1,"offset":2471},"end":{"line":39,"column":172,"offset":2642},"indent":[]}},{"type":"paragraph","children":[{"type":"text","value":"Read through ","position":{"start":{"line":41,"column":1,"offset":2644},"end":{"line":41,"column":14,"offset":2657},"indent":[]}},{"type":"link","title":null,"url":"/operation/log-files","children":[{"type":"text","value":"Log Files","position":{"start":{"line":41,"column":15,"offset":2658},"end":{"line":41,"column":24,"offset":2667},"indent":[]}}],"position":{"start":{"line":41,"column":14,"offset":2657},"end":{"line":41,"column":47,"offset":2690},"indent":[]}},{"type":"text","value":" section of ","position":{"start":{"line":41,"column":47,"offset":2690},"end":{"line":41,"column":59,"offset":2702},"indent":[]}},{"type":"link","title":null,"url":"/operation/overview","children":[{"type":"text","value":"Operation","position":{"start":{"line":41,"column":60,"offset":2703},"end":{"line":41,"column":69,"offset":2712},"indent":[]}}],"position":{"start":{"line":41,"column":59,"offset":2702},"end":{"line":41,"column":91,"offset":2734},"indent":[]}},{"type":"text","value":".","position":{"start":{"line":41,"column":91,"offset":2734},"end":{"line":41,"column":92,"offset":2735},"indent":[]}}],"position":{"start":{"line":41,"column":1,"offset":2644},"end":{"line":41,"column":92,"offset":2735},"indent":[]}},{"type":"heading","depth":2,"children":[{"type":"text","value":"🤓 Developer documentation","position":{"start":{"line":43,"column":4,"offset":2740},"end":{"line":43,"column":30,"offset":2766},"indent":[]}}],"position":{"start":{"line":43,"column":1,"offset":2737},"end":{"line":43,"column":30,"offset":2766},"indent":[]}},{"type":"paragraph","children":[{"type":"text","value":"We created a guide that walks you through preparing your development environment and developing Hummingbot using Linux, macOS, and Windows.","position":{"start":{"line":45,"column":1,"offset":2768},"end":{"line":45,"column":140,"offset":2907},"indent":[]}}],"position":{"start":{"line":45,"column":1,"offset":2768},"end":{"line":45,"column":140,"offset":2907},"indent":[]}},{"type":"paragraph","children":[{"type":"text","value":"Read through our Developer Manual for more information.","position":{"start":{"line":47,"column":1,"offset":2909},"end":{"line":47,"column":56,"offset":2964},"indent":[]}}],"position":{"start":{"line":47,"column":1,"offset":2909},"end":{"line":47,"column":56,"offset":2964},"indent":[]}},{"type":"heading","depth":2,"children":[{"type":"text","value":"📓 Documentation updates","position":{"start":{"line":49,"column":4,"offset":2969},"end":{"line":49,"column":28,"offset":2993},"indent":[]}}],"position":{"start":{"line":49,"column":1,"offset":2966},"end":{"line":49,"column":28,"offset":2993},"indent":[]}},{"type":"paragraph","children":[{"type":"text","value":"Here we list other recent significant changes to Hummingbot docs:","position":{"start":{"line":51,"column":1,"offset":2995},"end":{"line":51,"column":66,"offset":3060},"indent":[]}}],"position":{"start":{"line":51,"column":1,"offset":2995},"end":{"line":51,"column":66,"offset":3060},"indent":[]}},{"type":"list","ordered":false,"start":null,"spread":false,"children":[{"type":"listItem","spread":false,"checked":null,"children":[{"type":"paragraph","children":[{"type":"text","value":"Updated quickstart guide and added GIF images for visual.\nAdded instructions on resetting forgotten passwords, transferring files from/to WSL, and downloading a previous version of Hummingbot in Windows.","position":{"start":{"line":53,"column":3,"offset":3064},"end":{"line":54,"column":148,"offset":3269},"indent":[3]}}],"position":{"start":{"line":53,"column":3,"offset":3064},"end":{"line":54,"column":148,"offset":3269},"indent":[3]}}],"position":{"start":{"line":53,"column":1,"offset":3062},"end":{"line":54,"column":148,"offset":3269},"indent":[1]}},{"type":"listItem","spread":false,"checked":null,"children":[{"type":"paragraph","children":[{"type":"text","value":"Also added steps on how to locate and map ","position":{"start":{"line":55,"column":3,"offset":3272},"end":{"line":55,"column":45,"offset":3314},"indent":[]}},{"type":"inlineCode","value":"data","position":{"start":{"line":55,"column":45,"offset":3314},"end":{"line":55,"column":51,"offset":3320},"indent":[]}},{"type":"text","value":" folder when using Docker.","position":{"start":{"line":55,"column":51,"offset":3320},"end":{"line":55,"column":77,"offset":3346},"indent":[]}}],"position":{"start":{"line":55,"column":3,"offset":3272},"end":{"line":55,"column":77,"offset":3346},"indent":[]}}],"position":{"start":{"line":55,"column":1,"offset":3270},"end":{"line":55,"column":77,"offset":3346},"indent":[]}},{"type":"listItem","spread":false,"checked":null,"children":[{"type":"paragraph","children":[{"type":"text","value":"Added information in Binance troubleshooting about Binance HTTP return codes 429 and 418, Binance API trading limits, and how to avoid these return codes when running Hummingbot.","position":{"start":{"line":56,"column":3,"offset":3349},"end":{"line":56,"column":181,"offset":3527},"indent":[]}}],"position":{"start":{"line":56,"column":3,"offset":3349},"end":{"line":56,"column":181,"offset":3527},"indent":[]}}],"position":{"start":{"line":56,"column":1,"offset":3347},"end":{"line":56,"column":181,"offset":3527},"indent":[]}},{"type":"listItem","spread":false,"checked":null,"children":[{"type":"paragraph","children":[{"type":"text","value":"More examples with images and explanation for ","position":{"start":{"line":57,"column":3,"offset":3530},"end":{"line":57,"column":49,"offset":3576},"indent":[]}},{"type":"link","title":null,"url":"https://docs.hummingbot.io/strategies/pure-market-making/#best-bid-ask-jumping","children":[{"type":"text","value":"best bid-ask jumping","position":{"start":{"line":57,"column":50,"offset":3577},"end":{"line":57,"column":70,"offset":3597},"indent":[]}}],"position":{"start":{"line":57,"column":49,"offset":3576},"end":{"line":57,"column":151,"offset":3678},"indent":[]}},{"type":"text","value":" in pure market-making strategy.","position":{"start":{"line":57,"column":151,"offset":3678},"end":{"line":57,"column":183,"offset":3710},"indent":[]}}],"position":{"start":{"line":57,"column":3,"offset":3530},"end":{"line":57,"column":183,"offset":3710},"indent":[]}}],"position":{"start":{"line":57,"column":1,"offset":3528},"end":{"line":57,"column":183,"offset":3710},"indent":[]}}],"position":{"start":{"line":53,"column":1,"offset":3062},"end":{"line":57,"column":183,"offset":3710},"indent":[1,1,1,1]}},{"type":"heading","depth":2,"children":[{"type":"text","value":"🐞 Other bug fixes","position":{"start":{"line":59,"column":4,"offset":3715},"end":{"line":59,"column":22,"offset":3733},"indent":[]}}],"position":{"start":{"line":59,"column":1,"offset":3712},"end":{"line":59,"column":22,"offset":3733},"indent":[]}},{"type":"paragraph","children":[{"type":"text","value":"Thanks to everyone who reported bugs! ","position":{"start":{"line":61,"column":1,"offset":3735},"end":{"line":61,"column":39,"offset":3773},"indent":[]}},{"type":"strong","children":[{"type":"text","value":"Note that we pay bug bounties to anyone who reports a bug that we end up fixing.","position":{"start":{"line":61,"column":41,"offset":3775},"end":{"line":61,"column":121,"offset":3855},"indent":[]}}],"position":{"start":{"line":61,"column":39,"offset":3773},"end":{"line":61,"column":123,"offset":3857},"indent":[]}}],"position":{"start":{"line":61,"column":1,"offset":3735},"end":{"line":61,"column":123,"offset":3857},"indent":[]}},{"type":"list","ordered":false,"start":null,"spread":false,"children":[{"type":"listItem","spread":false,"checked":null,"children":[{"type":"paragraph","children":[{"type":"text","value":"Fixed error when exporting trades in Windows: ","position":{"start":{"line":63,"column":3,"offset":3861},"end":{"line":63,"column":49,"offset":3907},"indent":[]}},{"type":"link","title":null,"url":"https://github.com/CoinAlpha/hummingbot/issues/1302","children":[{"type":"text","value":"#1302","position":{"start":{"line":63,"column":50,"offset":3908},"end":{"line":63,"column":55,"offset":3913},"indent":[]}}],"position":{"start":{"line":63,"column":49,"offset":3907},"end":{"line":63,"column":109,"offset":3967},"indent":[]}}],"position":{"start":{"line":63,"column":3,"offset":3861},"end":{"line":63,"column":109,"offset":3967},"indent":[]}}],"position":{"start":{"line":63,"column":1,"offset":3859},"end":{"line":63,"column":109,"offset":3967},"indent":[]}},{"type":"listItem","spread":false,"checked":null,"children":[{"type":"paragraph","children":[{"type":"text","value":"Fixed bug losing track of orders on Coinbase Pro: ","position":{"start":{"line":64,"column":3,"offset":3970},"end":{"line":64,"column":53,"offset":4020},"indent":[]}},{"type":"link","title":null,"url":"https://github.com/CoinAlpha/hummingbot/issues/1357","children":[{"type":"text","value":"#1357","position":{"start":{"line":64,"column":54,"offset":4021},"end":{"line":64,"column":59,"offset":4026},"indent":[]}}],"position":{"start":{"line":64,"column":53,"offset":4020},"end":{"line":64,"column":113,"offset":4080},"indent":[]}}],"position":{"start":{"line":64,"column":3,"offset":3970},"end":{"line":64,"column":113,"offset":4080},"indent":[]}}],"position":{"start":{"line":64,"column":1,"offset":3968},"end":{"line":64,"column":113,"offset":4080},"indent":[]}},{"type":"listItem","spread":false,"checked":null,"children":[{"type":"paragraph","children":[{"type":"text","value":"Fixed bug where Hummingbot keeps fetching status of non-existing orders in client: ","position":{"start":{"line":65,"column":3,"offset":4083},"end":{"line":65,"column":86,"offset":4166},"indent":[]}},{"type":"link","title":null,"url":"https://github.com/CoinAlpha/hummingbot/issues/1281","children":[{"type":"text","value":"#1281","position":{"start":{"line":65,"column":87,"offset":4167},"end":{"line":65,"column":92,"offset":4172},"indent":[]}}],"position":{"start":{"line":65,"column":86,"offset":4166},"end":{"line":65,"column":146,"offset":4226},"indent":[]}}],"position":{"start":{"line":65,"column":3,"offset":4083},"end":{"line":65,"column":146,"offset":4226},"indent":[]}}],"position":{"start":{"line":65,"column":1,"offset":4081},"end":{"line":65,"column":146,"offset":4226},"indent":[]}},{"type":"listItem","spread":false,"checked":null,"children":[{"type":"paragraph","children":[{"type":"text","value":"Fixed bug in Liquid connector on non-fiat quote asset: ","position":{"start":{"line":66,"column":3,"offset":4229},"end":{"line":66,"column":58,"offset":4284},"indent":[]}},{"type":"link","title":null,"url":"https://github.com/CoinAlpha/hummingbot/issues/1331","children":[{"type":"text","value":"#1331","position":{"start":{"line":66,"column":59,"offset":4285},"end":{"line":66,"column":64,"offset":4290},"indent":[]}}],"position":{"start":{"line":66,"column":58,"offset":4284},"end":{"line":66,"column":118,"offset":4344},"indent":[]}}],"position":{"start":{"line":66,"column":3,"offset":4229},"end":{"line":66,"column":118,"offset":4344},"indent":[]}}],"position":{"start":{"line":66,"column":1,"offset":4227},"end":{"line":66,"column":118,"offset":4344},"indent":[]}},{"type":"listItem","spread":false,"checked":null,"children":[{"type":"paragraph","children":[{"type":"text","value":"Fixed intermittent index errors with pure market making strategy causing orders not created: ","position":{"start":{"line":67,"column":3,"offset":4347},"end":{"line":67,"column":96,"offset":4440},"indent":[]}},{"type":"link","title":null,"url":"https://github.com/CoinAlpha/hummingbot/issues/1317","children":[{"type":"text","value":"#1317","position":{"start":{"line":67,"column":97,"offset":4441},"end":{"line":67,"column":102,"offset":4446},"indent":[]}}],"position":{"start":{"line":67,"column":96,"offset":4440},"end":{"line":67,"column":156,"offset":4500},"indent":[]}}],"position":{"start":{"line":67,"column":3,"offset":4347},"end":{"line":67,"column":156,"offset":4500},"indent":[]}}],"position":{"start":{"line":67,"column":1,"offset":4345},"end":{"line":67,"column":156,"offset":4500},"indent":[]}}],"position":{"start":{"line":63,"column":1,"offset":3859},"end":{"line":67,"column":156,"offset":4500},"indent":[1,1,1,1]}},{"type":"heading","depth":2,"children":[{"type":"text","value":"⚙️ Miscellaneous updates","position":{"start":{"line":69,"column":4,"offset":4505},"end":{"line":69,"column":28,"offset":4529},"indent":[]}}],"position":{"start":{"line":69,"column":1,"offset":4502},"end":{"line":69,"column":28,"offset":4529},"indent":[]}},{"type":"list","ordered":false,"start":null,"spread":false,"children":[{"type":"listItem","spread":false,"checked":null,"children":[{"type":"paragraph","children":[{"type":"text","value":"Added helpful links for liquidity mining and support to welcome screen","position":{"start":{"line":71,"column":3,"offset":4533},"end":{"line":71,"column":73,"offset":4603},"indent":[]}}],"position":{"start":{"line":71,"column":3,"offset":4533},"end":{"line":71,"column":73,"offset":4603},"indent":[]}}],"position":{"start":{"line":71,"column":1,"offset":4531},"end":{"line":71,"column":73,"offset":4603},"indent":[]}},{"type":"listItem","spread":false,"checked":null,"children":[{"type":"paragraph","children":[{"type":"text","value":"Handled crossed order on Bamboo Relay","position":{"start":{"line":72,"column":3,"offset":4606},"end":{"line":72,"column":40,"offset":4643},"indent":[]}}],"position":{"start":{"line":72,"column":3,"offset":4606},"end":{"line":72,"column":40,"offset":4643},"indent":[]}}],"position":{"start":{"line":72,"column":1,"offset":4604},"end":{"line":72,"column":40,"offset":4643},"indent":[]}},{"type":"listItem","spread":false,"checked":null,"children":[{"type":"paragraph","children":[{"type":"text","value":"Updated Coinbase Pro fees to 0.5% for both maker and taker orders","position":{"start":{"line":73,"column":3,"offset":4646},"end":{"line":73,"column":68,"offset":4711},"indent":[]}}],"position":{"start":{"line":73,"column":3,"offset":4646},"end":{"line":73,"column":68,"offset":4711},"indent":[]}}],"position":{"start":{"line":73,"column":1,"offset":4644},"end":{"line":73,"column":68,"offset":4711},"indent":[]}},{"type":"listItem","spread":false,"checked":null,"children":[{"type":"paragraph","children":[{"type":"text","value":"Quick fix on trading pair fetcher","position":{"start":{"line":74,"column":3,"offset":4714},"end":{"line":74,"column":36,"offset":4747},"indent":[]}}],"position":{"start":{"line":74,"column":3,"offset":4714},"end":{"line":74,"column":36,"offset":4747},"indent":[]}}],"position":{"start":{"line":74,"column":1,"offset":4712},"end":{"line":74,"column":36,"offset":4747},"indent":[]}},{"type":"listItem","spread":false,"checked":null,"children":[{"type":"paragraph","children":[{"type":"text","value":"Updated all ","position":{"start":{"line":75,"column":3,"offset":4750},"end":{"line":75,"column":15,"offset":4762},"indent":[]}},{"type":"inlineCode","value":"y/n","position":{"start":{"line":75,"column":15,"offset":4762},"end":{"line":75,"column":20,"offset":4767},"indent":[]}},{"type":"text","value":" prompts to ","position":{"start":{"line":75,"column":20,"offset":4767},"end":{"line":75,"column":32,"offset":4779},"indent":[]}},{"type":"inlineCode","value":"Yes/No","position":{"start":{"line":75,"column":32,"offset":4779},"end":{"line":75,"column":40,"offset":4787},"indent":[]}},{"type":"text","value":" in the Hummingbot client","position":{"start":{"line":75,"column":40,"offset":4787},"end":{"line":75,"column":65,"offset":4812},"indent":[]}}],"position":{"start":{"line":75,"column":3,"offset":4750},"end":{"line":75,"column":65,"offset":4812},"indent":[]}}],"position":{"start":{"line":75,"column":1,"offset":4748},"end":{"line":75,"column":65,"offset":4812},"indent":[]}}],"position":{"start":{"line":71,"column":1,"offset":4531},"end":{"line":75,"column":65,"offset":4812},"indent":[1,1,1,1]}},{"type":"heading","depth":2,"children":[{"type":"text","value":"🚀 Coming soon","position":{"start":{"line":77,"column":4,"offset":4817},"end":{"line":77,"column":18,"offset":4831},"indent":[]}}],"position":{"start":{"line":77,"column":1,"offset":4814},"end":{"line":77,"column":18,"offset":4831},"indent":[]}},{"type":"paragraph","children":[{"type":"text","value":"Here's what we are currently working on that we expect to ship in the next 2-8 weeks:","position":{"start":{"line":79,"column":1,"offset":4833},"end":{"line":79,"column":86,"offset":4918},"indent":[]}}],"position":{"start":{"line":79,"column":1,"offset":4833},"end":{"line":79,"column":86,"offset":4918},"indent":[]}},{"type":"list","ordered":false,"start":null,"spread":false,"children":[{"type":"listItem","spread":false,"checked":null,"children":[{"type":"paragraph","children":[{"type":"link","title":null,"url":"https://www.bitfinex.com/","children":[{"type":"text","value":"Bitfinex","position":{"start":{"line":81,"column":4,"offset":4923},"end":{"line":81,"column":12,"offset":4931},"indent":[]}}],"position":{"start":{"line":81,"column":3,"offset":4922},"end":{"line":81,"column":40,"offset":4959},"indent":[]}},{"type":"text","value":" connector (in progress ","position":{"start":{"line":81,"column":40,"offset":4959},"end":{"line":81,"column":64,"offset":4983},"indent":[]}},{"type":"link","title":null,"url":"https://github.com/CoinAlpha/hummingbot/pull/1227","children":[{"type":"text","value":"#1227","position":{"start":{"line":81,"column":65,"offset":4984},"end":{"line":81,"column":70,"offset":4989},"indent":[]}}],"position":{"start":{"line":81,"column":64,"offset":4983},"end":{"line":81,"column":122,"offset":5041},"indent":[]}},{"type":"text","value":", ","position":{"start":{"line":81,"column":122,"offset":5041},"end":{"line":81,"column":124,"offset":5043},"indent":[]}},{"type":"link","title":null,"url":"https://github.com/CoinAlpha/hummingbot/pull/1237","children":[{"type":"text","value":"#1237","position":{"start":{"line":81,"column":125,"offset":5044},"end":{"line":81,"column":130,"offset":5049},"indent":[]}}],"position":{"start":{"line":81,"column":124,"offset":5043},"end":{"line":81,"column":182,"offset":5101},"indent":[]}},{"type":"text","value":")","position":{"start":{"line":81,"column":182,"offset":5101},"end":{"line":81,"column":183,"offset":5102},"indent":[]}}],"position":{"start":{"line":81,"column":3,"offset":4922},"end":{"line":81,"column":183,"offset":5102},"indent":[]}}],"position":{"start":{"line":81,"column":1,"offset":4920},"end":{"line":81,"column":183,"offset":5102},"indent":[]}},{"type":"listItem","spread":false,"checked":null,"children":[{"type":"paragraph","children":[{"type":"link","title":null,"url":"https://hitbtc.com/","children":[{"type":"text","value":"HitBTC","position":{"start":{"line":82,"column":4,"offset":5106},"end":{"line":82,"column":10,"offset":5112},"indent":[]}}],"position":{"start":{"line":82,"column":3,"offset":5105},"end":{"line":82,"column":32,"offset":5134},"indent":[]}},{"type":"text","value":" connector (in progress ","position":{"start":{"line":82,"column":32,"offset":5134},"end":{"line":82,"column":56,"offset":5158},"indent":[]}},{"type":"link","title":null,"url":"https://github.com/CoinAlpha/hummingbot/pull/1224","children":[{"type":"text","value":"#1224","position":{"start":{"line":82,"column":57,"offset":5159},"end":{"line":82,"column":62,"offset":5164},"indent":[]}}],"position":{"start":{"line":82,"column":56,"offset":5158},"end":{"line":82,"column":114,"offset":5216},"indent":[]}},{"type":"text","value":")","position":{"start":{"line":82,"column":114,"offset":5216},"end":{"line":82,"column":115,"offset":5217},"indent":[]}}],"position":{"start":{"line":82,"column":3,"offset":5105},"end":{"line":82,"column":115,"offset":5217},"indent":[]}}],"position":{"start":{"line":82,"column":1,"offset":5103},"end":{"line":82,"column":115,"offset":5217},"indent":[]}},{"type":"listItem","spread":false,"checked":null,"children":[{"type":"paragraph","children":[{"type":"link","title":null,"url":"https://gate.io","children":[{"type":"text","value":"gate.io","position":{"start":{"line":83,"column":4,"offset":5221},"end":{"line":83,"column":11,"offset":5228},"indent":[]}}],"position":{"start":{"line":83,"column":3,"offset":5220},"end":{"line":83,"column":29,"offset":5246},"indent":[]}},{"type":"text","value":" connector","position":{"start":{"line":83,"column":29,"offset":5246},"end":{"line":83,"column":39,"offset":5256},"indent":[]}}],"position":{"start":{"line":83,"column":3,"offset":5220},"end":{"line":83,"column":39,"offset":5256},"indent":[]}}],"position":{"start":{"line":83,"column":1,"offset":5218},"end":{"line":83,"column":39,"offset":5256},"indent":[]}}],"position":{"start":{"line":81,"column":1,"offset":4920},"end":{"line":83,"column":39,"offset":5256},"indent":[1,1]}},{"type":"export","value":"export const _frontmatter = {\"title\":\"Version 0.23.0\"}","position":{"start":{"line":86,"column":1,"offset":5259},"end":{"line":86,"column":55,"offset":5313},"indent":[]}}],"position":{"start":{"line":1,"column":1,"offset":0},"end":{"line":86,"column":55,"offset":5313}}},"scopeImports":["import * as React from 'react'"],"scopeIdentifiers":["React"],"body":"function _extends() { _extends = Object.assign || function (target) { for (var i = 1; i < arguments.length; i++) { var source = arguments[i]; for (var key in source) { if (Object.prototype.hasOwnProperty.call(source, key)) { target[key] = source[key]; } } } return target; }; return _extends.apply(this, arguments); }\n\nfunction _objectWithoutProperties(source, excluded) { if (source == null) return {}; var target = _objectWithoutPropertiesLoose(source, excluded); var key, i; if (Object.getOwnPropertySymbols) { var sourceSymbolKeys = Object.getOwnPropertySymbols(source); for (i = 0; i < sourceSymbolKeys.length; i++) { key = sourceSymbolKeys[i]; if (excluded.indexOf(key) >= 0) continue; if (!Object.prototype.propertyIsEnumerable.call(source, key)) continue; target[key] = source[key]; } } return target; }\n\nfunction _objectWithoutPropertiesLoose(source, excluded) { if (source == null) return {}; var target = {}; var sourceKeys = Object.keys(source); var key, i; for (i = 0; i < sourceKeys.length; i++) { key = sourceKeys[i]; if (excluded.indexOf(key) >= 0) continue; target[key] = source[key]; } return target; }\n\n/* @jsxRuntime classic */\n\n/* @jsx mdx */\nvar _frontmatter = {\n  \"title\": \"Version 0.23.0\"\n};\nvar layoutProps = {\n  _frontmatter: _frontmatter\n};\nvar MDXLayout = \"wrapper\";\nreturn function MDXContent(_ref) {\n  var components = _ref.components,\n      props = _objectWithoutProperties(_ref, [\"components\"]);\n\n  return mdx(MDXLayout, _extends({}, layoutProps, props, {\n    components: components,\n    mdxType: \"MDXLayout\"\n  }), mdx(\"p\", null, \"\\uD83D\\uDE80 Welcome to \", mdx(\"code\", _extends({\n    parentName: \"p\"\n  }, {\n    \"className\": \"language-text\"\n  }), \"hummingbot\"), \" version 0.23.0! In this release, we are excited to announce the open beta of Liquidity Mining, a new connector, easier to use pure market-making strategy, and addressed a number of bugs.\"), mdx(\"h2\", {\n    \"id\": \"-liquidity-mining-open-beta\",\n    \"style\": {\n      \"position\": \"relative\"\n    }\n  }, mdx(\"a\", _extends({\n    parentName: \"h2\"\n  }, {\n    \"href\": \"#-liquidity-mining-open-beta\",\n    \"aria-label\": \" liquidity mining open beta permalink\",\n    \"className\": \"anchor before\"\n  }), mdx(\"svg\", _extends({\n    parentName: \"a\"\n  }, {\n    \"aria-hidden\": \"true\",\n    \"focusable\": \"false\",\n    \"height\": \"16\",\n    \"version\": \"1.1\",\n    \"viewBox\": \"0 0 16 16\",\n    \"width\": \"16\"\n  }), mdx(\"path\", _extends({\n    parentName: \"svg\"\n  }, {\n    \"fillRule\": \"evenodd\",\n    \"d\": \"M4 9h1v1H4c-1.5 0-3-1.69-3-3.5S2.55 3 4 3h4c1.45 0 3 1.69 3 3.5 0 1.41-.91 2.72-2 3.25V8.59c.58-.45 1-1.27 1-2.09C10 5.22 8.98 4 8 4H4c-.98 0-2 1.22-2 2.5S3 9 4 9zm9-3h-1v1h1c1 0 2 1.22 2 2.5S13.98 12 13 12H9c-.98 0-2-1.22-2-2.5 0-.83.42-1.64 1-2.09V6.25c-1.09.53-2 1.84-2 3.25C6 11.31 7.55 13 9 13h4c1.45 0 3-1.69 3-3.5S14.5 6 13 6z\"\n  })))), \"\\uD83C\\uDF0A\\u26CF Liquidity mining open beta\"), mdx(\"p\", null, \"We are excited to launch the Liquidity Mining Open Beta today! We welcome anyone interested in joining us during the 4-week testing period and try the \", mdx(\"a\", _extends({\n    parentName: \"p\"\n  }, {\n    \"href\": \"https://miners.hummingbot.io\"\n  }), \"Hummingbot Miners App\"), \". We will work hard to collect user feedback and fix bugs to provide a great user experience when we go live on March 2, 2020.\"), mdx(\"ul\", null, mdx(\"li\", {\n    parentName: \"ul\"\n  }, mdx(\"a\", _extends({\n    parentName: \"li\"\n  }, {\n    \"href\": \"https://hummingbot.io/liquidity-mining/\"\n  }), \"Learn more\"))), mdx(\"h3\", {\n    \"id\": \"🧪-user-testing-during-open-beta\",\n    \"style\": {\n      \"position\": \"relative\"\n    }\n  }, mdx(\"a\", _extends({\n    parentName: \"h3\"\n  }, {\n    \"href\": \"#%F0%9F%A7%AA-user-testing-during-open-beta\",\n    \"aria-label\": \"🧪 user testing during open beta permalink\",\n    \"className\": \"anchor before\"\n  }), mdx(\"svg\", _extends({\n    parentName: \"a\"\n  }, {\n    \"aria-hidden\": \"true\",\n    \"focusable\": \"false\",\n    \"height\": \"16\",\n    \"version\": \"1.1\",\n    \"viewBox\": \"0 0 16 16\",\n    \"width\": \"16\"\n  }), mdx(\"path\", _extends({\n    parentName: \"svg\"\n  }, {\n    \"fillRule\": \"evenodd\",\n    \"d\": \"M4 9h1v1H4c-1.5 0-3-1.69-3-3.5S2.55 3 4 3h4c1.45 0 3 1.69 3 3.5 0 1.41-.91 2.72-2 3.25V8.59c.58-.45 1-1.27 1-2.09C10 5.22 8.98 4 8 4H4c-.98 0-2 1.22-2 2.5S3 9 4 9zm9-3h-1v1h1c1 0 2 1.22 2 2.5S13.98 12 13 12H9c-.98 0-2-1.22-2-2.5 0-.83.42-1.64 1-2.09V6.25c-1.09.53-2 1.84-2 3.25C6 11.31 7.55 13 9 13h4c1.45 0 3-1.69 3-3.5S14.5 6 13 6z\"\n  })))), \"\\uD83E\\uDDEA User testing during open beta\"), mdx(\"p\", null, \"We are inviting interested users to join our dedicated user testing program during the Open Beta period. Testers will receive \", mdx(\"strong\", {\n    parentName: \"p\"\n  }, \"0.1 ETH\"), \" for their time.\"), mdx(\"p\", null, \"For users who want to participate, please fill out this form. We\\u2019ll reach out to you soon!\"), mdx(\"p\", null, \"Please refer to the following links and resources for more information:\"), mdx(\"ul\", null, mdx(\"li\", {\n    parentName: \"ul\"\n  }, mdx(\"a\", _extends({\n    parentName: \"li\"\n  }, {\n    \"href\": \"https://miners.hummingbot.io\"\n  }), \"Hummingbot Miners\")), mdx(\"li\", {\n    parentName: \"ul\"\n  }, mdx(\"a\", _extends({\n    parentName: \"li\"\n  }, {\n    \"href\": \"https://docs.hummingbot.io/miner/liquidity-mining/overview/\"\n  }), \"Participation Guide\")), mdx(\"li\", {\n    parentName: \"ul\"\n  }, mdx(\"a\", _extends({\n    parentName: \"li\"\n  }, {\n    \"href\": \"https://support.hummingbot.io/hc/en-us\"\n  }), \"Hummingbot Help Center\")), mdx(\"li\", {\n    parentName: \"ul\"\n  }, mdx(\"a\", _extends({\n    parentName: \"li\"\n  }, {\n    \"href\": \"https://hummingbot.io/liquidity-mining-policy/\"\n  }), \"Liquidity Mining Policy\"))), mdx(\"h2\", {\n    \"id\": \"-pure-market-making-configuration-simplified\",\n    \"style\": {\n      \"position\": \"relative\"\n    }\n  }, mdx(\"a\", _extends({\n    parentName: \"h2\"\n  }, {\n    \"href\": \"#-pure-market-making-configuration-simplified\",\n    \"aria-label\": \" pure market making configuration simplified permalink\",\n    \"className\": \"anchor before\"\n  }), mdx(\"svg\", _extends({\n    parentName: \"a\"\n  }, {\n    \"aria-hidden\": \"true\",\n    \"focusable\": \"false\",\n    \"height\": \"16\",\n    \"version\": \"1.1\",\n    \"viewBox\": \"0 0 16 16\",\n    \"width\": \"16\"\n  }), mdx(\"path\", _extends({\n    parentName: \"svg\"\n  }, {\n    \"fillRule\": \"evenodd\",\n    \"d\": \"M4 9h1v1H4c-1.5 0-3-1.69-3-3.5S2.55 3 4 3h4c1.45 0 3 1.69 3 3.5 0 1.41-.91 2.72-2 3.25V8.59c.58-.45 1-1.27 1-2.09C10 5.22 8.98 4 8 4H4c-.98 0-2 1.22-2 2.5S3 9 4 9zm9-3h-1v1h1c1 0 2 1.22 2 2.5S13.98 12 13 12H9c-.98 0-2-1.22-2-2.5 0-.83.42-1.64 1-2.09V6.25c-1.09.53-2 1.84-2 3.25C6 11.31 7.55 13 9 13h4c1.45 0 3-1.69 3-3.5S14.5 6 13 6z\"\n  })))), \"\\uD83D\\uDCCA Pure market-making configuration simplified\"), mdx(\"p\", null, \"Pure market-making now has a basic/advanced split that will only prompt during the configuration of the basic parameters such as the exchange name, trading pair, bid/ask spreads, cancel order wait time, and order amount.\"), mdx(\"p\", null, \"Users can configure the advanced features of this strategy by entering \", mdx(\"code\", _extends({\n    parentName: \"p\"\n  }, {\n    \"className\": \"language-text\"\n  }), \"Yes\"), \" when prompted via \", mdx(\"code\", _extends({\n    parentName: \"p\"\n  }, {\n    \"className\": \"language-text\"\n  }), \"config <parameter>\"), \" command in Hummingbot, or by editing the strategy config file.\"), mdx(\"p\", null, \"More information about \", mdx(\"a\", _extends({\n    parentName: \"p\"\n  }, {\n    \"href\": \"https://docs.hummingbot.io/strategies/pure-market-making/#basic-mode\"\n  }), \"Basic Mode\"), \" and \", mdx(\"a\", _extends({\n    parentName: \"p\"\n  }, {\n    \"href\": \"https://docs.hummingbot.io/strategies/pure-market-making/#advanced-mode\"\n  }), \"Advanced Mode\"), \" of Pure Market Making in our User Manual.\"), mdx(\"h2\", {\n    \"id\": \"-new-kucoin-connector\",\n    \"style\": {\n      \"position\": \"relative\"\n    }\n  }, mdx(\"a\", _extends({\n    parentName: \"h2\"\n  }, {\n    \"href\": \"#-new-kucoin-connector\",\n    \"aria-label\": \" new kucoin connector permalink\",\n    \"className\": \"anchor before\"\n  }), mdx(\"svg\", _extends({\n    parentName: \"a\"\n  }, {\n    \"aria-hidden\": \"true\",\n    \"focusable\": \"false\",\n    \"height\": \"16\",\n    \"version\": \"1.1\",\n    \"viewBox\": \"0 0 16 16\",\n    \"width\": \"16\"\n  }), mdx(\"path\", _extends({\n    parentName: \"svg\"\n  }, {\n    \"fillRule\": \"evenodd\",\n    \"d\": \"M4 9h1v1H4c-1.5 0-3-1.69-3-3.5S2.55 3 4 3h4c1.45 0 3 1.69 3 3.5 0 1.41-.91 2.72-2 3.25V8.59c.58-.45 1-1.27 1-2.09C10 5.22 8.98 4 8 4H4c-.98 0-2 1.22-2 2.5S3 9 4 9zm9-3h-1v1h1c1 0 2 1.22 2 2.5S13.98 12 13 12H9c-.98 0-2-1.22-2-2.5 0-.83.42-1.64 1-2.09V6.25c-1.09.53-2 1.84-2 3.25C6 11.31 7.55 13 9 13h4c1.45 0 3-1.69 3-3.5S14.5 6 13 6z\"\n  })))), \"\\uD83D\\uDD17 New KuCoin connector\"), mdx(\"p\", null, \"Hummingbot now supports \", mdx(\"a\", _extends({\n    parentName: \"p\"\n  }, {\n    \"href\": \"https://www.kucoin.com/\"\n  }), \"KuCoin\"), \" exchange! Nicknamed the \\\"People's Exchange\\\"\\u200B, Kucoin is easy to use for novice investors and in-depth enough for crypto enthusiasts. It has one of the world\\u2019s most impressive trading pair selections, a wide range of alt coins with more than 300 trading pairs and are adding new ones regularly.\"), mdx(\"p\", null, \"Read more about using KuCoin connector in the \", mdx(\"a\", _extends({\n    parentName: \"p\"\n  }, {\n    \"href\": \"/spot-connectors/kucoin/\"\n  }), \"User Manual\"), \".\"), mdx(\"h2\", {\n    \"id\": \"-error-log-collection\",\n    \"style\": {\n      \"position\": \"relative\"\n    }\n  }, mdx(\"a\", _extends({\n    parentName: \"h2\"\n  }, {\n    \"href\": \"#-error-log-collection\",\n    \"aria-label\": \" error log collection permalink\",\n    \"className\": \"anchor before\"\n  }), mdx(\"svg\", _extends({\n    parentName: \"a\"\n  }, {\n    \"aria-hidden\": \"true\",\n    \"focusable\": \"false\",\n    \"height\": \"16\",\n    \"version\": \"1.1\",\n    \"viewBox\": \"0 0 16 16\",\n    \"width\": \"16\"\n  }), mdx(\"path\", _extends({\n    parentName: \"svg\"\n  }, {\n    \"fillRule\": \"evenodd\",\n    \"d\": \"M4 9h1v1H4c-1.5 0-3-1.69-3-3.5S2.55 3 4 3h4c1.45 0 3 1.69 3 3.5 0 1.41-.91 2.72-2 3.25V8.59c.58-.45 1-1.27 1-2.09C10 5.22 8.98 4 8 4H4c-.98 0-2 1.22-2 2.5S3 9 4 9zm9-3h-1v1h1c1 0 2 1.22 2 2.5S13.98 12 13 12H9c-.98 0-2-1.22-2-2.5 0-.83.42-1.64 1-2.09V6.25c-1.09.53-2 1.84-2 3.25C6 11.31 7.55 13 9 13h4c1.45 0 3-1.69 3-3.5S14.5 6 13 6z\"\n  })))), \"\\uD83D\\uDCDC Error log collection\"), mdx(\"p\", null, \"Instead of using the old \", mdx(\"code\", _extends({\n    parentName: \"p\"\n  }, {\n    \"className\": \"language-text\"\n  }), \"hummingbot_logs.yml\"), \" templates for sending logs, we now added a prompt in Hummingbot that allows users to enable or disabled sending errors logs.\"), mdx(\"p\", null, \"Read through \", mdx(\"a\", _extends({\n    parentName: \"p\"\n  }, {\n    \"href\": \"/operation/log-files\"\n  }), \"Log Files\"), \" section of \", mdx(\"a\", _extends({\n    parentName: \"p\"\n  }, {\n    \"href\": \"/operation/overview\"\n  }), \"Operation\"), \".\"), mdx(\"h2\", {\n    \"id\": \"-developer-documentation\",\n    \"style\": {\n      \"position\": \"relative\"\n    }\n  }, mdx(\"a\", _extends({\n    parentName: \"h2\"\n  }, {\n    \"href\": \"#-developer-documentation\",\n    \"aria-label\": \" developer documentation permalink\",\n    \"className\": \"anchor before\"\n  }), mdx(\"svg\", _extends({\n    parentName: \"a\"\n  }, {\n    \"aria-hidden\": \"true\",\n    \"focusable\": \"false\",\n    \"height\": \"16\",\n    \"version\": \"1.1\",\n    \"viewBox\": \"0 0 16 16\",\n    \"width\": \"16\"\n  }), mdx(\"path\", _extends({\n    parentName: \"svg\"\n  }, {\n    \"fillRule\": \"evenodd\",\n    \"d\": \"M4 9h1v1H4c-1.5 0-3-1.69-3-3.5S2.55 3 4 3h4c1.45 0 3 1.69 3 3.5 0 1.41-.91 2.72-2 3.25V8.59c.58-.45 1-1.27 1-2.09C10 5.22 8.98 4 8 4H4c-.98 0-2 1.22-2 2.5S3 9 4 9zm9-3h-1v1h1c1 0 2 1.22 2 2.5S13.98 12 13 12H9c-.98 0-2-1.22-2-2.5 0-.83.42-1.64 1-2.09V6.25c-1.09.53-2 1.84-2 3.25C6 11.31 7.55 13 9 13h4c1.45 0 3-1.69 3-3.5S14.5 6 13 6z\"\n  })))), \"\\uD83E\\uDD13 Developer documentation\"), mdx(\"p\", null, \"We created a guide that walks you through preparing your development environment and developing Hummingbot using Linux, macOS, and Windows.\"), mdx(\"p\", null, \"Read through our Developer Manual for more information.\"), mdx(\"h2\", {\n    \"id\": \"-documentation-updates\",\n    \"style\": {\n      \"position\": \"relative\"\n    }\n  }, mdx(\"a\", _extends({\n    parentName: \"h2\"\n  }, {\n    \"href\": \"#-documentation-updates\",\n    \"aria-label\": \" documentation updates permalink\",\n    \"className\": \"anchor before\"\n  }), mdx(\"svg\", _extends({\n    parentName: \"a\"\n  }, {\n    \"aria-hidden\": \"true\",\n    \"focusable\": \"false\",\n    \"height\": \"16\",\n    \"version\": \"1.1\",\n    \"viewBox\": \"0 0 16 16\",\n    \"width\": \"16\"\n  }), mdx(\"path\", _extends({\n    parentName: \"svg\"\n  }, {\n    \"fillRule\": \"evenodd\",\n    \"d\": \"M4 9h1v1H4c-1.5 0-3-1.69-3-3.5S2.55 3 4 3h4c1.45 0 3 1.69 3 3.5 0 1.41-.91 2.72-2 3.25V8.59c.58-.45 1-1.27 1-2.09C10 5.22 8.98 4 8 4H4c-.98 0-2 1.22-2 2.5S3 9 4 9zm9-3h-1v1h1c1 0 2 1.22 2 2.5S13.98 12 13 12H9c-.98 0-2-1.22-2-2.5 0-.83.42-1.64 1-2.09V6.25c-1.09.53-2 1.84-2 3.25C6 11.31 7.55 13 9 13h4c1.45 0 3-1.69 3-3.5S14.5 6 13 6z\"\n  })))), \"\\uD83D\\uDCD3 Documentation updates\"), mdx(\"p\", null, \"Here we list other recent significant changes to Hummingbot docs:\"), mdx(\"ul\", null, mdx(\"li\", {\n    parentName: \"ul\"\n  }, \"Updated quickstart guide and added GIF images for visual.\\nAdded instructions on resetting forgotten passwords, transferring files from/to WSL, and downloading a previous version of Hummingbot in Windows.\"), mdx(\"li\", {\n    parentName: \"ul\"\n  }, \"Also added steps on how to locate and map \", mdx(\"code\", _extends({\n    parentName: \"li\"\n  }, {\n    \"className\": \"language-text\"\n  }), \"data\"), \" folder when using Docker.\"), mdx(\"li\", {\n    parentName: \"ul\"\n  }, \"Added information in Binance troubleshooting about Binance HTTP return codes 429 and 418, Binance API trading limits, and how to avoid these return codes when running Hummingbot.\"), mdx(\"li\", {\n    parentName: \"ul\"\n  }, \"More examples with images and explanation for \", mdx(\"a\", _extends({\n    parentName: \"li\"\n  }, {\n    \"href\": \"https://docs.hummingbot.io/strategies/pure-market-making/#best-bid-ask-jumping\"\n  }), \"best bid-ask jumping\"), \" in pure market-making strategy.\")), mdx(\"h2\", {\n    \"id\": \"-other-bug-fixes\",\n    \"style\": {\n      \"position\": \"relative\"\n    }\n  }, mdx(\"a\", _extends({\n    parentName: \"h2\"\n  }, {\n    \"href\": \"#-other-bug-fixes\",\n    \"aria-label\": \" other bug fixes permalink\",\n    \"className\": \"anchor before\"\n  }), mdx(\"svg\", _extends({\n    parentName: \"a\"\n  }, {\n    \"aria-hidden\": \"true\",\n    \"focusable\": \"false\",\n    \"height\": \"16\",\n    \"version\": \"1.1\",\n    \"viewBox\": \"0 0 16 16\",\n    \"width\": \"16\"\n  }), mdx(\"path\", _extends({\n    parentName: \"svg\"\n  }, {\n    \"fillRule\": \"evenodd\",\n    \"d\": \"M4 9h1v1H4c-1.5 0-3-1.69-3-3.5S2.55 3 4 3h4c1.45 0 3 1.69 3 3.5 0 1.41-.91 2.72-2 3.25V8.59c.58-.45 1-1.27 1-2.09C10 5.22 8.98 4 8 4H4c-.98 0-2 1.22-2 2.5S3 9 4 9zm9-3h-1v1h1c1 0 2 1.22 2 2.5S13.98 12 13 12H9c-.98 0-2-1.22-2-2.5 0-.83.42-1.64 1-2.09V6.25c-1.09.53-2 1.84-2 3.25C6 11.31 7.55 13 9 13h4c1.45 0 3-1.69 3-3.5S14.5 6 13 6z\"\n  })))), \"\\uD83D\\uDC1E Other bug fixes\"), mdx(\"p\", null, \"Thanks to everyone who reported bugs! \", mdx(\"strong\", {\n    parentName: \"p\"\n  }, \"Note that we pay bug bounties to anyone who reports a bug that we end up fixing.\")), mdx(\"ul\", null, mdx(\"li\", {\n    parentName: \"ul\"\n  }, \"Fixed error when exporting trades in Windows: \", mdx(\"a\", _extends({\n    parentName: \"li\"\n  }, {\n    \"href\": \"https://github.com/CoinAlpha/hummingbot/issues/1302\"\n  }), \"#1302\")), mdx(\"li\", {\n    parentName: \"ul\"\n  }, \"Fixed bug losing track of orders on Coinbase Pro: \", mdx(\"a\", _extends({\n    parentName: \"li\"\n  }, {\n    \"href\": \"https://github.com/CoinAlpha/hummingbot/issues/1357\"\n  }), \"#1357\")), mdx(\"li\", {\n    parentName: \"ul\"\n  }, \"Fixed bug where Hummingbot keeps fetching status of non-existing orders in client: \", mdx(\"a\", _extends({\n    parentName: \"li\"\n  }, {\n    \"href\": \"https://github.com/CoinAlpha/hummingbot/issues/1281\"\n  }), \"#1281\")), mdx(\"li\", {\n    parentName: \"ul\"\n  }, \"Fixed bug in Liquid connector on non-fiat quote asset: \", mdx(\"a\", _extends({\n    parentName: \"li\"\n  }, {\n    \"href\": \"https://github.com/CoinAlpha/hummingbot/issues/1331\"\n  }), \"#1331\")), mdx(\"li\", {\n    parentName: \"ul\"\n  }, \"Fixed intermittent index errors with pure market making strategy causing orders not created: \", mdx(\"a\", _extends({\n    parentName: \"li\"\n  }, {\n    \"href\": \"https://github.com/CoinAlpha/hummingbot/issues/1317\"\n  }), \"#1317\"))), mdx(\"h2\", {\n    \"id\": \"️-miscellaneous-updates\",\n    \"style\": {\n      \"position\": \"relative\"\n    }\n  }, mdx(\"a\", _extends({\n    parentName: \"h2\"\n  }, {\n    \"href\": \"#%EF%B8%8F-miscellaneous-updates\",\n    \"aria-label\": \"️ miscellaneous updates permalink\",\n    \"className\": \"anchor before\"\n  }), mdx(\"svg\", _extends({\n    parentName: \"a\"\n  }, {\n    \"aria-hidden\": \"true\",\n    \"focusable\": \"false\",\n    \"height\": \"16\",\n    \"version\": \"1.1\",\n    \"viewBox\": \"0 0 16 16\",\n    \"width\": \"16\"\n  }), mdx(\"path\", _extends({\n    parentName: \"svg\"\n  }, {\n    \"fillRule\": \"evenodd\",\n    \"d\": \"M4 9h1v1H4c-1.5 0-3-1.69-3-3.5S2.55 3 4 3h4c1.45 0 3 1.69 3 3.5 0 1.41-.91 2.72-2 3.25V8.59c.58-.45 1-1.27 1-2.09C10 5.22 8.98 4 8 4H4c-.98 0-2 1.22-2 2.5S3 9 4 9zm9-3h-1v1h1c1 0 2 1.22 2 2.5S13.98 12 13 12H9c-.98 0-2-1.22-2-2.5 0-.83.42-1.64 1-2.09V6.25c-1.09.53-2 1.84-2 3.25C6 11.31 7.55 13 9 13h4c1.45 0 3-1.69 3-3.5S14.5 6 13 6z\"\n  })))), \"\\u2699\\uFE0F Miscellaneous updates\"), mdx(\"ul\", null, mdx(\"li\", {\n    parentName: \"ul\"\n  }, \"Added helpful links for liquidity mining and support to welcome screen\"), mdx(\"li\", {\n    parentName: \"ul\"\n  }, \"Handled crossed order on Bamboo Relay\"), mdx(\"li\", {\n    parentName: \"ul\"\n  }, \"Updated Coinbase Pro fees to 0.5% for both maker and taker orders\"), mdx(\"li\", {\n    parentName: \"ul\"\n  }, \"Quick fix on trading pair fetcher\"), mdx(\"li\", {\n    parentName: \"ul\"\n  }, \"Updated all \", mdx(\"code\", _extends({\n    parentName: \"li\"\n  }, {\n    \"className\": \"language-text\"\n  }), \"y/n\"), \" prompts to \", mdx(\"code\", _extends({\n    parentName: \"li\"\n  }, {\n    \"className\": \"language-text\"\n  }), \"Yes/No\"), \" in the Hummingbot client\")), mdx(\"h2\", {\n    \"id\": \"-coming-soon\",\n    \"style\": {\n      \"position\": \"relative\"\n    }\n  }, mdx(\"a\", _extends({\n    parentName: \"h2\"\n  }, {\n    \"href\": \"#-coming-soon\",\n    \"aria-label\": \" coming soon permalink\",\n    \"className\": \"anchor before\"\n  }), mdx(\"svg\", _extends({\n    parentName: \"a\"\n  }, {\n    \"aria-hidden\": \"true\",\n    \"focusable\": \"false\",\n    \"height\": \"16\",\n    \"version\": \"1.1\",\n    \"viewBox\": \"0 0 16 16\",\n    \"width\": \"16\"\n  }), mdx(\"path\", _extends({\n    parentName: \"svg\"\n  }, {\n    \"fillRule\": \"evenodd\",\n    \"d\": \"M4 9h1v1H4c-1.5 0-3-1.69-3-3.5S2.55 3 4 3h4c1.45 0 3 1.69 3 3.5 0 1.41-.91 2.72-2 3.25V8.59c.58-.45 1-1.27 1-2.09C10 5.22 8.98 4 8 4H4c-.98 0-2 1.22-2 2.5S3 9 4 9zm9-3h-1v1h1c1 0 2 1.22 2 2.5S13.98 12 13 12H9c-.98 0-2-1.22-2-2.5 0-.83.42-1.64 1-2.09V6.25c-1.09.53-2 1.84-2 3.25C6 11.31 7.55 13 9 13h4c1.45 0 3-1.69 3-3.5S14.5 6 13 6z\"\n  })))), \"\\uD83D\\uDE80 Coming soon\"), mdx(\"p\", null, \"Here's what we are currently working on that we expect to ship in the next 2-8 weeks:\"), mdx(\"ul\", null, mdx(\"li\", {\n    parentName: \"ul\"\n  }, mdx(\"a\", _extends({\n    parentName: \"li\"\n  }, {\n    \"href\": \"https://www.bitfinex.com/\"\n  }), \"Bitfinex\"), \" connector (in progress \", mdx(\"a\", _extends({\n    parentName: \"li\"\n  }, {\n    \"href\": \"https://github.com/CoinAlpha/hummingbot/pull/1227\"\n  }), \"#1227\"), \", \", mdx(\"a\", _extends({\n    parentName: \"li\"\n  }, {\n    \"href\": \"https://github.com/CoinAlpha/hummingbot/pull/1237\"\n  }), \"#1237\"), \")\"), mdx(\"li\", {\n    parentName: \"ul\"\n  }, mdx(\"a\", _extends({\n    parentName: \"li\"\n  }, {\n    \"href\": \"https://hitbtc.com/\"\n  }), \"HitBTC\"), \" connector (in progress \", mdx(\"a\", _extends({\n    parentName: \"li\"\n  }, {\n    \"href\": \"https://github.com/CoinAlpha/hummingbot/pull/1224\"\n  }), \"#1224\"), \")\"), mdx(\"li\", {\n    parentName: \"ul\"\n  }, mdx(\"a\", _extends({\n    parentName: \"li\"\n  }, {\n    \"href\": \"https://gate.io\"\n  }), \"gate.io\"), \" connector\")));\n}\n;\nMDXContent.isMDXComponent = true;","rawMDXOutput":"/* @jsx mdx */\nimport { mdx } from '@mdx-js/react';\n/* @jsxRuntime classic */\n/* @jsx mdx */\n\nexport const _frontmatter = {\n  \"title\": \"Version 0.23.0\"\n};\n\nconst layoutProps = {\n  _frontmatter\n};\nconst MDXLayout = \"wrapper\"\nexport default function MDXContent({\n  components,\n  ...props\n}) {\n  return <MDXLayout {...layoutProps} {...props} components={components} mdxType=\"MDXLayout\">\n    <p>{`🚀 Welcome to `}<code parentName=\"p\" {...{\n        \"className\": \"language-text\"\n      }}>{`hummingbot`}</code>{` version 0.23.0! In this release, we are excited to announce the open beta of Liquidity Mining, a new connector, easier to use pure market-making strategy, and addressed a number of bugs.`}</p>\n    <h2 {...{\n      \"id\": \"-liquidity-mining-open-beta\",\n      \"style\": {\n        \"position\": \"relative\"\n      }\n    }}><a parentName=\"h2\" {...{\n        \"href\": \"#-liquidity-mining-open-beta\",\n        \"aria-label\": \" liquidity mining open beta permalink\",\n        \"className\": \"anchor before\"\n      }}><svg parentName=\"a\" {...{\n          \"aria-hidden\": \"true\",\n          \"focusable\": \"false\",\n          \"height\": \"16\",\n          \"version\": \"1.1\",\n          \"viewBox\": \"0 0 16 16\",\n          \"width\": \"16\"\n        }}><path parentName=\"svg\" {...{\n            \"fillRule\": \"evenodd\",\n            \"d\": \"M4 9h1v1H4c-1.5 0-3-1.69-3-3.5S2.55 3 4 3h4c1.45 0 3 1.69 3 3.5 0 1.41-.91 2.72-2 3.25V8.59c.58-.45 1-1.27 1-2.09C10 5.22 8.98 4 8 4H4c-.98 0-2 1.22-2 2.5S3 9 4 9zm9-3h-1v1h1c1 0 2 1.22 2 2.5S13.98 12 13 12H9c-.98 0-2-1.22-2-2.5 0-.83.42-1.64 1-2.09V6.25c-1.09.53-2 1.84-2 3.25C6 11.31 7.55 13 9 13h4c1.45 0 3-1.69 3-3.5S14.5 6 13 6z\"\n          }}></path></svg></a>{`🌊⛏ Liquidity mining open beta`}</h2>\n    <p>{`We are excited to launch the Liquidity Mining Open Beta today! We welcome anyone interested in joining us during the 4-week testing period and try the `}<a parentName=\"p\" {...{\n        \"href\": \"https://miners.hummingbot.io\"\n      }}>{`Hummingbot Miners App`}</a>{`. We will work hard to collect user feedback and fix bugs to provide a great user experience when we go live on March 2, 2020.`}</p>\n    <ul>\n      <li parentName=\"ul\"><a parentName=\"li\" {...{\n          \"href\": \"https://hummingbot.io/liquidity-mining/\"\n        }}>{`Learn more`}</a></li>\n    </ul>\n    <h3 {...{\n      \"id\": \"🧪-user-testing-during-open-beta\",\n      \"style\": {\n        \"position\": \"relative\"\n      }\n    }}><a parentName=\"h3\" {...{\n        \"href\": \"#%F0%9F%A7%AA-user-testing-during-open-beta\",\n        \"aria-label\": \"🧪 user testing during open beta permalink\",\n        \"className\": \"anchor before\"\n      }}><svg parentName=\"a\" {...{\n          \"aria-hidden\": \"true\",\n          \"focusable\": \"false\",\n          \"height\": \"16\",\n          \"version\": \"1.1\",\n          \"viewBox\": \"0 0 16 16\",\n          \"width\": \"16\"\n        }}><path parentName=\"svg\" {...{\n            \"fillRule\": \"evenodd\",\n            \"d\": \"M4 9h1v1H4c-1.5 0-3-1.69-3-3.5S2.55 3 4 3h4c1.45 0 3 1.69 3 3.5 0 1.41-.91 2.72-2 3.25V8.59c.58-.45 1-1.27 1-2.09C10 5.22 8.98 4 8 4H4c-.98 0-2 1.22-2 2.5S3 9 4 9zm9-3h-1v1h1c1 0 2 1.22 2 2.5S13.98 12 13 12H9c-.98 0-2-1.22-2-2.5 0-.83.42-1.64 1-2.09V6.25c-1.09.53-2 1.84-2 3.25C6 11.31 7.55 13 9 13h4c1.45 0 3-1.69 3-3.5S14.5 6 13 6z\"\n          }}></path></svg></a>{`🧪 User testing during open beta`}</h3>\n    <p>{`We are inviting interested users to join our dedicated user testing program during the Open Beta period. Testers will receive `}<strong parentName=\"p\">{`0.1 ETH`}</strong>{` for their time.`}</p>\n    <p>{`For users who want to participate, please fill out this form. We’ll reach out to you soon!`}</p>\n    <p>{`Please refer to the following links and resources for more information:`}</p>\n    <ul>\n      <li parentName=\"ul\"><a parentName=\"li\" {...{\n          \"href\": \"https://miners.hummingbot.io\"\n        }}>{`Hummingbot Miners`}</a></li>\n      <li parentName=\"ul\"><a parentName=\"li\" {...{\n          \"href\": \"https://docs.hummingbot.io/miner/liquidity-mining/overview/\"\n        }}>{`Participation Guide`}</a></li>\n      <li parentName=\"ul\"><a parentName=\"li\" {...{\n          \"href\": \"https://support.hummingbot.io/hc/en-us\"\n        }}>{`Hummingbot Help Center`}</a></li>\n      <li parentName=\"ul\"><a parentName=\"li\" {...{\n          \"href\": \"https://hummingbot.io/liquidity-mining-policy/\"\n        }}>{`Liquidity Mining Policy`}</a></li>\n    </ul>\n    <h2 {...{\n      \"id\": \"-pure-market-making-configuration-simplified\",\n      \"style\": {\n        \"position\": \"relative\"\n      }\n    }}><a parentName=\"h2\" {...{\n        \"href\": \"#-pure-market-making-configuration-simplified\",\n        \"aria-label\": \" pure market making configuration simplified permalink\",\n        \"className\": \"anchor before\"\n      }}><svg parentName=\"a\" {...{\n          \"aria-hidden\": \"true\",\n          \"focusable\": \"false\",\n          \"height\": \"16\",\n          \"version\": \"1.1\",\n          \"viewBox\": \"0 0 16 16\",\n          \"width\": \"16\"\n        }}><path parentName=\"svg\" {...{\n            \"fillRule\": \"evenodd\",\n            \"d\": \"M4 9h1v1H4c-1.5 0-3-1.69-3-3.5S2.55 3 4 3h4c1.45 0 3 1.69 3 3.5 0 1.41-.91 2.72-2 3.25V8.59c.58-.45 1-1.27 1-2.09C10 5.22 8.98 4 8 4H4c-.98 0-2 1.22-2 2.5S3 9 4 9zm9-3h-1v1h1c1 0 2 1.22 2 2.5S13.98 12 13 12H9c-.98 0-2-1.22-2-2.5 0-.83.42-1.64 1-2.09V6.25c-1.09.53-2 1.84-2 3.25C6 11.31 7.55 13 9 13h4c1.45 0 3-1.69 3-3.5S14.5 6 13 6z\"\n          }}></path></svg></a>{`📊 Pure market-making configuration simplified`}</h2>\n    <p>{`Pure market-making now has a basic/advanced split that will only prompt during the configuration of the basic parameters such as the exchange name, trading pair, bid/ask spreads, cancel order wait time, and order amount.`}</p>\n    <p>{`Users can configure the advanced features of this strategy by entering `}<code parentName=\"p\" {...{\n        \"className\": \"language-text\"\n      }}>{`Yes`}</code>{` when prompted via `}<code parentName=\"p\" {...{\n        \"className\": \"language-text\"\n      }}>{`config <parameter>`}</code>{` command in Hummingbot, or by editing the strategy config file.`}</p>\n    <p>{`More information about `}<a parentName=\"p\" {...{\n        \"href\": \"https://docs.hummingbot.io/strategies/pure-market-making/#basic-mode\"\n      }}>{`Basic Mode`}</a>{` and `}<a parentName=\"p\" {...{\n        \"href\": \"https://docs.hummingbot.io/strategies/pure-market-making/#advanced-mode\"\n      }}>{`Advanced Mode`}</a>{` of Pure Market Making in our User Manual.`}</p>\n    <h2 {...{\n      \"id\": \"-new-kucoin-connector\",\n      \"style\": {\n        \"position\": \"relative\"\n      }\n    }}><a parentName=\"h2\" {...{\n        \"href\": \"#-new-kucoin-connector\",\n        \"aria-label\": \" new kucoin connector permalink\",\n        \"className\": \"anchor before\"\n      }}><svg parentName=\"a\" {...{\n          \"aria-hidden\": \"true\",\n          \"focusable\": \"false\",\n          \"height\": \"16\",\n          \"version\": \"1.1\",\n          \"viewBox\": \"0 0 16 16\",\n          \"width\": \"16\"\n        }}><path parentName=\"svg\" {...{\n            \"fillRule\": \"evenodd\",\n            \"d\": \"M4 9h1v1H4c-1.5 0-3-1.69-3-3.5S2.55 3 4 3h4c1.45 0 3 1.69 3 3.5 0 1.41-.91 2.72-2 3.25V8.59c.58-.45 1-1.27 1-2.09C10 5.22 8.98 4 8 4H4c-.98 0-2 1.22-2 2.5S3 9 4 9zm9-3h-1v1h1c1 0 2 1.22 2 2.5S13.98 12 13 12H9c-.98 0-2-1.22-2-2.5 0-.83.42-1.64 1-2.09V6.25c-1.09.53-2 1.84-2 3.25C6 11.31 7.55 13 9 13h4c1.45 0 3-1.69 3-3.5S14.5 6 13 6z\"\n          }}></path></svg></a>{`🔗 New KuCoin connector`}</h2>\n    <p>{`Hummingbot now supports `}<a parentName=\"p\" {...{\n        \"href\": \"https://www.kucoin.com/\"\n      }}>{`KuCoin`}</a>{` exchange! Nicknamed the \"People's Exchange\"​, Kucoin is easy to use for novice investors and in-depth enough for crypto enthusiasts. It has one of the world’s most impressive trading pair selections, a wide range of alt coins with more than 300 trading pairs and are adding new ones regularly.`}</p>\n    <p>{`Read more about using KuCoin connector in the `}<a parentName=\"p\" {...{\n        \"href\": \"/spot-connectors/kucoin/\"\n      }}>{`User Manual`}</a>{`.`}</p>\n    <h2 {...{\n      \"id\": \"-error-log-collection\",\n      \"style\": {\n        \"position\": \"relative\"\n      }\n    }}><a parentName=\"h2\" {...{\n        \"href\": \"#-error-log-collection\",\n        \"aria-label\": \" error log collection permalink\",\n        \"className\": \"anchor before\"\n      }}><svg parentName=\"a\" {...{\n          \"aria-hidden\": \"true\",\n          \"focusable\": \"false\",\n          \"height\": \"16\",\n          \"version\": \"1.1\",\n          \"viewBox\": \"0 0 16 16\",\n          \"width\": \"16\"\n        }}><path parentName=\"svg\" {...{\n            \"fillRule\": \"evenodd\",\n            \"d\": \"M4 9h1v1H4c-1.5 0-3-1.69-3-3.5S2.55 3 4 3h4c1.45 0 3 1.69 3 3.5 0 1.41-.91 2.72-2 3.25V8.59c.58-.45 1-1.27 1-2.09C10 5.22 8.98 4 8 4H4c-.98 0-2 1.22-2 2.5S3 9 4 9zm9-3h-1v1h1c1 0 2 1.22 2 2.5S13.98 12 13 12H9c-.98 0-2-1.22-2-2.5 0-.83.42-1.64 1-2.09V6.25c-1.09.53-2 1.84-2 3.25C6 11.31 7.55 13 9 13h4c1.45 0 3-1.69 3-3.5S14.5 6 13 6z\"\n          }}></path></svg></a>{`📜 Error log collection`}</h2>\n    <p>{`Instead of using the old `}<code parentName=\"p\" {...{\n        \"className\": \"language-text\"\n      }}>{`hummingbot_logs.yml`}</code>{` templates for sending logs, we now added a prompt in Hummingbot that allows users to enable or disabled sending errors logs.`}</p>\n    <p>{`Read through `}<a parentName=\"p\" {...{\n        \"href\": \"/operation/log-files\"\n      }}>{`Log Files`}</a>{` section of `}<a parentName=\"p\" {...{\n        \"href\": \"/operation/overview\"\n      }}>{`Operation`}</a>{`.`}</p>\n    <h2 {...{\n      \"id\": \"-developer-documentation\",\n      \"style\": {\n        \"position\": \"relative\"\n      }\n    }}><a parentName=\"h2\" {...{\n        \"href\": \"#-developer-documentation\",\n        \"aria-label\": \" developer documentation permalink\",\n        \"className\": \"anchor before\"\n      }}><svg parentName=\"a\" {...{\n          \"aria-hidden\": \"true\",\n          \"focusable\": \"false\",\n          \"height\": \"16\",\n          \"version\": \"1.1\",\n          \"viewBox\": \"0 0 16 16\",\n          \"width\": \"16\"\n        }}><path parentName=\"svg\" {...{\n            \"fillRule\": \"evenodd\",\n            \"d\": \"M4 9h1v1H4c-1.5 0-3-1.69-3-3.5S2.55 3 4 3h4c1.45 0 3 1.69 3 3.5 0 1.41-.91 2.72-2 3.25V8.59c.58-.45 1-1.27 1-2.09C10 5.22 8.98 4 8 4H4c-.98 0-2 1.22-2 2.5S3 9 4 9zm9-3h-1v1h1c1 0 2 1.22 2 2.5S13.98 12 13 12H9c-.98 0-2-1.22-2-2.5 0-.83.42-1.64 1-2.09V6.25c-1.09.53-2 1.84-2 3.25C6 11.31 7.55 13 9 13h4c1.45 0 3-1.69 3-3.5S14.5 6 13 6z\"\n          }}></path></svg></a>{`🤓 Developer documentation`}</h2>\n    <p>{`We created a guide that walks you through preparing your development environment and developing Hummingbot using Linux, macOS, and Windows.`}</p>\n    <p>{`Read through our Developer Manual for more information.`}</p>\n    <h2 {...{\n      \"id\": \"-documentation-updates\",\n      \"style\": {\n        \"position\": \"relative\"\n      }\n    }}><a parentName=\"h2\" {...{\n        \"href\": \"#-documentation-updates\",\n        \"aria-label\": \" documentation updates permalink\",\n        \"className\": \"anchor before\"\n      }}><svg parentName=\"a\" {...{\n          \"aria-hidden\": \"true\",\n          \"focusable\": \"false\",\n          \"height\": \"16\",\n          \"version\": \"1.1\",\n          \"viewBox\": \"0 0 16 16\",\n          \"width\": \"16\"\n        }}><path parentName=\"svg\" {...{\n            \"fillRule\": \"evenodd\",\n            \"d\": \"M4 9h1v1H4c-1.5 0-3-1.69-3-3.5S2.55 3 4 3h4c1.45 0 3 1.69 3 3.5 0 1.41-.91 2.72-2 3.25V8.59c.58-.45 1-1.27 1-2.09C10 5.22 8.98 4 8 4H4c-.98 0-2 1.22-2 2.5S3 9 4 9zm9-3h-1v1h1c1 0 2 1.22 2 2.5S13.98 12 13 12H9c-.98 0-2-1.22-2-2.5 0-.83.42-1.64 1-2.09V6.25c-1.09.53-2 1.84-2 3.25C6 11.31 7.55 13 9 13h4c1.45 0 3-1.69 3-3.5S14.5 6 13 6z\"\n          }}></path></svg></a>{`📓 Documentation updates`}</h2>\n    <p>{`Here we list other recent significant changes to Hummingbot docs:`}</p>\n    <ul>\n      <li parentName=\"ul\">{`Updated quickstart guide and added GIF images for visual.\nAdded instructions on resetting forgotten passwords, transferring files from/to WSL, and downloading a previous version of Hummingbot in Windows.`}</li>\n      <li parentName=\"ul\">{`Also added steps on how to locate and map `}<code parentName=\"li\" {...{\n          \"className\": \"language-text\"\n        }}>{`data`}</code>{` folder when using Docker.`}</li>\n      <li parentName=\"ul\">{`Added information in Binance troubleshooting about Binance HTTP return codes 429 and 418, Binance API trading limits, and how to avoid these return codes when running Hummingbot.`}</li>\n      <li parentName=\"ul\">{`More examples with images and explanation for `}<a parentName=\"li\" {...{\n          \"href\": \"https://docs.hummingbot.io/strategies/pure-market-making/#best-bid-ask-jumping\"\n        }}>{`best bid-ask jumping`}</a>{` in pure market-making strategy.`}</li>\n    </ul>\n    <h2 {...{\n      \"id\": \"-other-bug-fixes\",\n      \"style\": {\n        \"position\": \"relative\"\n      }\n    }}><a parentName=\"h2\" {...{\n        \"href\": \"#-other-bug-fixes\",\n        \"aria-label\": \" other bug fixes permalink\",\n        \"className\": \"anchor before\"\n      }}><svg parentName=\"a\" {...{\n          \"aria-hidden\": \"true\",\n          \"focusable\": \"false\",\n          \"height\": \"16\",\n          \"version\": \"1.1\",\n          \"viewBox\": \"0 0 16 16\",\n          \"width\": \"16\"\n        }}><path parentName=\"svg\" {...{\n            \"fillRule\": \"evenodd\",\n            \"d\": \"M4 9h1v1H4c-1.5 0-3-1.69-3-3.5S2.55 3 4 3h4c1.45 0 3 1.69 3 3.5 0 1.41-.91 2.72-2 3.25V8.59c.58-.45 1-1.27 1-2.09C10 5.22 8.98 4 8 4H4c-.98 0-2 1.22-2 2.5S3 9 4 9zm9-3h-1v1h1c1 0 2 1.22 2 2.5S13.98 12 13 12H9c-.98 0-2-1.22-2-2.5 0-.83.42-1.64 1-2.09V6.25c-1.09.53-2 1.84-2 3.25C6 11.31 7.55 13 9 13h4c1.45 0 3-1.69 3-3.5S14.5 6 13 6z\"\n          }}></path></svg></a>{`🐞 Other bug fixes`}</h2>\n    <p>{`Thanks to everyone who reported bugs! `}<strong parentName=\"p\">{`Note that we pay bug bounties to anyone who reports a bug that we end up fixing.`}</strong></p>\n    <ul>\n      <li parentName=\"ul\">{`Fixed error when exporting trades in Windows: `}<a parentName=\"li\" {...{\n          \"href\": \"https://github.com/CoinAlpha/hummingbot/issues/1302\"\n        }}>{`#1302`}</a></li>\n      <li parentName=\"ul\">{`Fixed bug losing track of orders on Coinbase Pro: `}<a parentName=\"li\" {...{\n          \"href\": \"https://github.com/CoinAlpha/hummingbot/issues/1357\"\n        }}>{`#1357`}</a></li>\n      <li parentName=\"ul\">{`Fixed bug where Hummingbot keeps fetching status of non-existing orders in client: `}<a parentName=\"li\" {...{\n          \"href\": \"https://github.com/CoinAlpha/hummingbot/issues/1281\"\n        }}>{`#1281`}</a></li>\n      <li parentName=\"ul\">{`Fixed bug in Liquid connector on non-fiat quote asset: `}<a parentName=\"li\" {...{\n          \"href\": \"https://github.com/CoinAlpha/hummingbot/issues/1331\"\n        }}>{`#1331`}</a></li>\n      <li parentName=\"ul\">{`Fixed intermittent index errors with pure market making strategy causing orders not created: `}<a parentName=\"li\" {...{\n          \"href\": \"https://github.com/CoinAlpha/hummingbot/issues/1317\"\n        }}>{`#1317`}</a></li>\n    </ul>\n    <h2 {...{\n      \"id\": \"️-miscellaneous-updates\",\n      \"style\": {\n        \"position\": \"relative\"\n      }\n    }}><a parentName=\"h2\" {...{\n        \"href\": \"#%EF%B8%8F-miscellaneous-updates\",\n        \"aria-label\": \"️ miscellaneous updates permalink\",\n        \"className\": \"anchor before\"\n      }}><svg parentName=\"a\" {...{\n          \"aria-hidden\": \"true\",\n          \"focusable\": \"false\",\n          \"height\": \"16\",\n          \"version\": \"1.1\",\n          \"viewBox\": \"0 0 16 16\",\n          \"width\": \"16\"\n        }}><path parentName=\"svg\" {...{\n            \"fillRule\": \"evenodd\",\n            \"d\": \"M4 9h1v1H4c-1.5 0-3-1.69-3-3.5S2.55 3 4 3h4c1.45 0 3 1.69 3 3.5 0 1.41-.91 2.72-2 3.25V8.59c.58-.45 1-1.27 1-2.09C10 5.22 8.98 4 8 4H4c-.98 0-2 1.22-2 2.5S3 9 4 9zm9-3h-1v1h1c1 0 2 1.22 2 2.5S13.98 12 13 12H9c-.98 0-2-1.22-2-2.5 0-.83.42-1.64 1-2.09V6.25c-1.09.53-2 1.84-2 3.25C6 11.31 7.55 13 9 13h4c1.45 0 3-1.69 3-3.5S14.5 6 13 6z\"\n          }}></path></svg></a>{`⚙️ Miscellaneous updates`}</h2>\n    <ul>\n      <li parentName=\"ul\">{`Added helpful links for liquidity mining and support to welcome screen`}</li>\n      <li parentName=\"ul\">{`Handled crossed order on Bamboo Relay`}</li>\n      <li parentName=\"ul\">{`Updated Coinbase Pro fees to 0.5% for both maker and taker orders`}</li>\n      <li parentName=\"ul\">{`Quick fix on trading pair fetcher`}</li>\n      <li parentName=\"ul\">{`Updated all `}<code parentName=\"li\" {...{\n          \"className\": \"language-text\"\n        }}>{`y/n`}</code>{` prompts to `}<code parentName=\"li\" {...{\n          \"className\": \"language-text\"\n        }}>{`Yes/No`}</code>{` in the Hummingbot client`}</li>\n    </ul>\n    <h2 {...{\n      \"id\": \"-coming-soon\",\n      \"style\": {\n        \"position\": \"relative\"\n      }\n    }}><a parentName=\"h2\" {...{\n        \"href\": \"#-coming-soon\",\n        \"aria-label\": \" coming soon permalink\",\n        \"className\": \"anchor before\"\n      }}><svg parentName=\"a\" {...{\n          \"aria-hidden\": \"true\",\n          \"focusable\": \"false\",\n          \"height\": \"16\",\n          \"version\": \"1.1\",\n          \"viewBox\": \"0 0 16 16\",\n          \"width\": \"16\"\n        }}><path parentName=\"svg\" {...{\n            \"fillRule\": \"evenodd\",\n            \"d\": \"M4 9h1v1H4c-1.5 0-3-1.69-3-3.5S2.55 3 4 3h4c1.45 0 3 1.69 3 3.5 0 1.41-.91 2.72-2 3.25V8.59c.58-.45 1-1.27 1-2.09C10 5.22 8.98 4 8 4H4c-.98 0-2 1.22-2 2.5S3 9 4 9zm9-3h-1v1h1c1 0 2 1.22 2 2.5S13.98 12 13 12H9c-.98 0-2-1.22-2-2.5 0-.83.42-1.64 1-2.09V6.25c-1.09.53-2 1.84-2 3.25C6 11.31 7.55 13 9 13h4c1.45 0 3-1.69 3-3.5S14.5 6 13 6z\"\n          }}></path></svg></a>{`🚀 Coming soon`}</h2>\n    <p>{`Here's what we are currently working on that we expect to ship in the next 2-8 weeks:`}</p>\n    <ul>\n      <li parentName=\"ul\"><a parentName=\"li\" {...{\n          \"href\": \"https://www.bitfinex.com/\"\n        }}>{`Bitfinex`}</a>{` connector (in progress `}<a parentName=\"li\" {...{\n          \"href\": \"https://github.com/CoinAlpha/hummingbot/pull/1227\"\n        }}>{`#1227`}</a>{`, `}<a parentName=\"li\" {...{\n          \"href\": \"https://github.com/CoinAlpha/hummingbot/pull/1237\"\n        }}>{`#1237`}</a>{`)`}</li>\n      <li parentName=\"ul\"><a parentName=\"li\" {...{\n          \"href\": \"https://hitbtc.com/\"\n        }}>{`HitBTC`}</a>{` connector (in progress `}<a parentName=\"li\" {...{\n          \"href\": \"https://github.com/CoinAlpha/hummingbot/pull/1224\"\n        }}>{`#1224`}</a>{`)`}</li>\n      <li parentName=\"ul\"><a parentName=\"li\" {...{\n          \"href\": \"https://gate.io\"\n        }}>{`gate.io`}</a>{` connector`}</li>\n    </ul>\n\n    </MDXLayout>;\n}\n\n;\nMDXContent.isMDXComponent = true;"}}